{
"mjm6rwepm7y5enifqz3iavgi":["callmewumple","Wumple (Comms Closed)"],
"t6k4hvumatymtywgqnld6jkr":["comfortablywumm","ComfortablyWumm"],
"kaicfg3p55agjve6mu7admnn":["criticalthought","Mark (Wumpy) McCaw"],
"dg3hu2xbxsxhj26fgu2lr7o2":["dablue","Wumbo Cumbo"],
"frnjytcb3pjrkh5svrv5uhk2":["grumpismcwumpis","GrumpisMcWumpis"],
"lipu3xftfi5kh2awkgh4wtwq":["hexwumbo","Hex: Wumbo"],
"tawylm2fcimed52o2krgltac":["iamwumbologist","I Am The Wumbologist (accept no substitutes)"],
"l4mapiipozs2jezlwtlxh5gt":["inkspecco","wumbles about"],
"g4qdfmvseiu3t6r24lqs6jjg":["kumawuma","Kuma_Wuma"],
"pmt3srngabgpuaolvhlibvvi":["moondog.live","Umby Wumby, the Poggy Doggy"],
"4is6rp7nmhrk7zj5wi6upv4p":["mrwumpel","Mr. Wumpel"],
"yspjpcyvojtzunf7ayjd3kdr":["mugwump","Wump!"],
"27i43wgkdyawbboyrdjyen5l":["nsfw.umby.dog","🔞 Umbybutt Wumbybutt 🐶🦴"],
"yg7oyt4ikgnmkkf34hrqhatr":["umby.dog","Umby Wumby 🐶💜"],
"qtb7ugzlrrnqadznlfuctnra":["werewolfnobody","Wumbo"],
"r5avzproj3x2qoxy7wbfyuc6":["wombuswumbo","Wombus Wumbo"],
"bwem6yl4mujdq76dczk6kwni":["wummi2903","Wummi2903"],
"e6j3h6ai34343r5mya5qsvx3":["wumother","Reneé Watkins"],
"gypgr5xethah4um4gwfqoe27":["wumpadash","wumpadash"],
"kb43j7x6dcxlfyi6yh5inrlo":["wumnaket","Свята Мученія"],
"yct7tykuprprmdqbolr2oab6":["wumpagem","WumpaGem"],
"numncczsvi6guntr2yjpy74j":["wumpajuice","Wumpa Juice "],
"mayddwfh3vi2klhc2uw33q2l":"wump",
"gf67bmv3ofukh2hsh3hkzgtv":["wumpus","Smith"],
"4irlfifnajc3qldhjul5bsax":["wumbulon","wumbulon"],
"hu7dzytd6t4jnqiztzaqpcwi":"wumbo",
"peugiiqagtfzx5dxcshupvsw":["wumbonize","Tim "],
"irj2qm6ibwysibst52dyuxlf":["wumbologize","Widget"],
"znk4hn6elw4hnlnyyef2h5so":"wumpushunter",
"x7v4pxg7bbfdge7arxwhnnj7":["wumbird","Brooke"],
"3dyv2kr7ranatwopk6bkf4zu":["wuming","nameless "],
"3zpsfqxnccchomyr6na3we6y":["wumi","WUMI"],
"cl7deinjarcc5qnw2gae2lkb":["wum19sn","nak"],
"lt2hyiqnjuhieyxcjrsra5qo":["wumbl3.xyz","wumbl3.xyz"],
"llfuo3bwnq53atf2e2p5vgxt":["wumiaow","Whoomeow"],
"qrvbrddow33kg3mua43q644l":["wum","Wum"],
"l7qg5haxn3xdjrv2asgj44r2":["wumwolf","Lumi"],
"sg6nw2rlpnj2ocfny5jagl5b":"wuming71663",
"mjfva4aqywegeehum63rnp2k":["wumpflumpem","Wump Flumpem"],
"v7fgdth7h5qdi2o5la5xvcu6":"wummi",
"aulbcm3sbw43dfo7ax4oizbv":"wumpaspaceprincess",
"57d7ggn7yjxtsiz6ryheau7w":"wumbulous",
"nc3nkntamfpfq4423nlmzmi4":["wumpabro","CharlieHachi"],
"bwulns25xriewin7pcfrgv25":"wuming716625",
"mjt46vyy5mlacelhfo5xm34k":"wumbo6116",
"j2hzcdm5pbobagrd6erg6gei":["wumpusplushie","Wumpus Plushie"],
"d3il7hguk345rmzngmfruzgl":["wumepitz","Wumé🍕"],
"4f72iasa2ka65n4j7gswctml":["wumfubble","Wubble"],
"e55pyvwlo7rngqxcjvqobyjb":["wumpel","Wumpel"],
"ihpwimq7yh6deqfze45ges7r":["wumpflump","WumpFlump"],
"fgbbd3coi4xampd74eld22tc":"wuming716622",
"urkzq3nseyi5uvpla5p77dkv":["wumbograyson","Wumbo"],
"vtzesdteiltie372n3r32xnf":"wumbvleromble",
"vtayejengw5hx5nywv7j5sjt":["wuw217","Wumms und Wirkung 217"],
"2jeeyttmphbl3itmiiw2xibd":["wuminglover666"," 🔥wuminglover666🔥"],
"75bz2t6m3htonr6b3v43rjom":"wumonline"
}
