{
"bzvdune543pa7nbwrarjikdn":["118ween","Jun"],
"iiaghmbnuhyea47ifpc4pvpb":["0xluigi","weegee"],
"zzbvzkuvgqwtyf2ttf7jcoyl":["420weedteen","Kelsey ;)"],
"b3niphtrtulvu56i3m4wcwnr":["69-weed","jͭaͪyͤ"],
"rp2c6be6cuzttljfuhdkq7jq":["4dayweek","4 Day Week Campaign"],
"a25kujul453sey4firsz56ni":["1thingaweek.com","1 Thing A Week"],
"asctgykbhzi6uykcjtmu6kqd":["2weeks0326","2JU"],
"iic3k22yp5mwmmsr2nb2dcqu":"15weetbix",
"dc4ufbjigaauooixi7qbr427":["4starsonly","Wee"],
"66rn6hgxcpod7disvrjgarzg":["5weetdream5","하나데 루나"],
"36g5aoae7wlqmlwc6iigasbl":["5708ski","5708ski (Weezer male)"],
"6yt7p4se6u25nw774xteucab":["5weetalpenfee1","MaRia ☕️🐾🐕"],
"z46nalb6rnuwmstffhitg4to":["3r1c888","Weenor"],
"p32ksnuoyvsuxiu4axvgm6xb":["2weevils","Patrick Langdon"],
"pb7cm7pnmngs2wlas6ug5jqf":["abyssalbrews.com","AbyssalBrews | Weekly Magic Items for D&D and PF2E"],
"gupbf37i2kigb7nlqyerq2er":["abnormality.is","Abnormality - Trick-Or-Treat Week"],
"aidioknicmt4xu3zyxickp6w":["aditimallya","Weeb ? Who? Me? "],
"fiiry6dcqbxr2rgw6vhz6yti":["adamdewees","Adam DeWees"],
"biyyjhm3rv5dzdd5pybrwtfn":["adjproyectos","A.D.J. Proyectos Audiovisuales (TDC Weekend, Aeterna, Cutrecon)"],
"vgblf6owe4dfmaw5u2fsq7ro":["adamweek","Adam Week"],
"w7zwvgcyhayplpuk4muhsald":["aeneadumgenetrx","Kro-ween"],
"55lzmi33vpc4qnfk5k2a3xc2":["ahhweebo","AhhWeebo"],
"ghwvtvdepmoutxndxcpl6cfv":["ajobpickard","Amanda Pickard #WeePonder"],
"igtk5has3i7vksp56c7mov42":["alcremy","weetzie rat"],
"sg5i2wgvwsd3iuhjg6sauyol":["alaskanweeb","Alaskan Weeb (Spooky)"],
"mqxbfs2g22kvm5hgpyjmvmj5":["al-wee","AL-WEE"],
"riy746ljoj6g3vzluak6vooe":["alyssawees","Alyssa Wees"],
"i5ouliop7dvrp22ueuywzj42":["alphusdoes","Alphus Weenie"],
"wr4l5kca257nlgujhz27ax7l":["alexaelartworks","𝘼𝙡𝙚𝙭𝙖𝙚𝙡 🦄🌸🤍 Japan Weekend Barcelona 23"],
"pqmcnxahdupw57kaasqrgebf":["amlw.dev","Anthony Weems"],
"u3debbzlautxdcmk75vo2afc":["amandadeweesauthor","Amanda DeWees"],
"kejmflbpy72dhsvjym2ne3bh":["amyweeks","Amy Weeks"],
"hviuvnf7yqlw5fo32bwrfurx":["amyweezer","Amy Weezer Fan"],
"a4hjabbby7k4p5ollpj3axj4":["andrewthehuman","Wee Gay Fella"],
"qakcxa66lvcf7b7z7fmrg5b2":["andystrongxxx","Andy Strong 🔜 FLL Pig Week"],
"wn2iohgqdkgv4d356lpuc5gw":["annaweezer","Anna Weezer"],
"b4yar2fkwocukjmwmmuhkg7z":["anacweeks","Ana Catalano Weeks"],
"q3a5kair6j2lywvou4q7jahp":["annewrites","Anne O'Ween"],
"gh3vfepxkrfks2trdjb6vayr":["andreadworkin","andrea dworkin for the weekend"],
"hfnhcxax4moawwzkrdjvwa2q":["aot-sick-weekend","AoT Sick Shit Weekend"],
"46h6myoxafdsvoeybymfyoxq":["artificialholly","Holly.ween.👻🎃."],
"gsn6upybz4tv6ncvdu7hzetl":["astrogrrrl69","Beanee Weenee"],
"4sbrenukzwf3tzxgsmknikfe":["astrids","Astrid je-weet-wel"],
"5543tbe7vz5h2cwizlhaf2we":["autobotjazzweek","Jazz Week"],
"g7yxlfqzjfacympfyllabucf":["avder","Ren the Weedcat"],
"4cuarg6puy6aa7v7tkwyqa54":["aweeklasttuesday","A Week Last Tuesday"],
"gcoverps6zus7phpqlrbfu7o":["awfuldumbass","monster of the week"],
"dlyrmwnjjpud3cc54nezyxcc":["aweeks007","Aaron Weeks"],
"4bqonuwdbz4rowsi22jrnszj":["awacon","Anime Weekend Atlanta"],
"jbmww2qedfpgut4mczta4n3n":["aweeger","Andreas Weeger"],
"3niqdbi643ftn3r4nshprlej":["bananacana","weenzoli"],
"klrplhsakrkthat4rriqmu26":["batertater420","WEED DADDY"],
"x2vqsllr4jvhyhnnlhu64qvx":["bastiwee","BastiWee"],
"r64wzjtkimyq4vkiddzuu6no":["bcwildfirewkly","BC Wildfire Weekly"],
"nywda5acxcsmrcmxklytlp5l":["bethweese","Beth Weese"],
"zfrpbi4u36r6izbmfmf57egt":["benjaminweekley","Benjamin Weekley, Ph.D."],
"zmfr2jk7svfgorvbfbahlohi":["beargirl","wee ajay "],
"qlmipqjo5hcin2fi5wid46tj":["beanusbasketweens","Beanus Weens"],
"2avuj72j2uakdwcthbjvuvdu":["bearshoesfive","Weel"],
"vctmfwvzrpuebl7xnsnhqe3z":["billzuka","Bill Zuka (Debuting This Week)"],
"vvtfwffcsdkinypqpsl7yz2b":["blsweek","BingLiuShen Week"],
"wprbhg5cnojigtubbn6abahq":["boner","Weed"],
"szoesjwcmiqwpqvloxvcb2c3":["bowmanfox","Bowman Ween"],
"hoieukkwhcqnkrznswq5mms6":["boognishrising","Aaron's Dean Ween stan account "],
"sjtdhxv47kmgum7ojsg2rul2":["bobweeks","Bob Weeks"],
"5qveijmaudrkd3nnrif3mn6t":["bonezel","Bad Bunz 🔜 Doggy Weekend"],
"amzrvkbwkfbtkxfnbjgoqyep":["bottombingheweek","Bottom Binghe Week '23 (Nov 12-19)"],
"osrmarflruaspe6x7ocdqlik":["brandonweeks.com","Brandon Weeks"],
"nrf5hn3mjnouwki5tvkaftd2":["brianweeden","Brian Weeden"],
"4h3udrqbfhb4n7t62pmtj4xe":["bre4kingbad","Grim weeper"],
"56jqx4sxmb2s5tda5ocml2ts":["brokewaluigi","out of weed"],
"y56sxlhxdtutunit45nw5evj":["bud.weedstar.social","Bud Weedstar, Private Eye"],
"as4be6u4ej4hhgmtyxcf3rl7":["bugmanbelfast","Wee Neil"],
"kbpv76xvzi4qfe74h5u5txlp":["caitvw","Caitlin Vander Weele, PhD"],
"uoxuszl6bntifv7arjo7nemc":["carikat","WeedKat 🏳️‍⚧️✊🏾🔞100% that Bitch."],
"xfl5sfopfvjagbsannawayc3":["camphowloween","Camp Howl-O-Ween"],
"6kxbg7bqobjherwajqt5g2lf":["captainweeks","Captain Weeks"],
"ae3bmka7dywnt65odzzjfvho":["chrisweedpiano","Chris Weed"],
"xq5cwg7mclm2xdbdbpij4y27":["chrisintheweeds","Chris in the weeds"],
"amnxo2xxwlfduw4yef3c5umw":["chaoticweevil","Chaotic Weevil"],
"k6y4mzflrezzbjc5tbe3juwq":["chrisweeden","Chris Weeden"],
"vbieqm4giy2zhnn2jc6xhxsj":["chubweeg","weeg"],
"dnwngkuft2eehs2wg3p2ezv5":["chilumiweek","Chilumi Week"],
"asyxssrdw7dlnkua3ltgh55g":["charltheweeb","CharlTheWeeb"],
"qkvqy2zjqylfdcw2vtxvaj4f":["chichhibap","OohWeeeee"],
"c6t64jouedwz45qd5xoycw3y":["cinechallenges","Weekly MovieChallenge"],
"ymliu5czolwrxskgdr2gwnto":["ckolonko","Chris Kolonko-Weet"],
"fxlcqzf7brhmz7im2qua35zb":["classiccatmemes","Mattmew Weebson | Average Zenos Simp"],
"ogpi55febs3q6ygrjsnvb7fq":["claireweekley","Claire Weekley"],
"4d6oqxikotrvf4azpldzenzg":["cludub","Chrissy Weeks"],
"dmdqjeonmiggnougfmzl5l6h":["cloverino420","Weed Doge"],
"52hvozsujezmkqadlqi2tmqh":["coprophagy","da weed mouse "],
"zlpjhz3azsl272ctqfqa57md":["coolnerdweedshow","Cool Nerd Weed Show"],
"hzajqmtsqdsxhoo53p65xoqt":["craigweeknotend","It's The Week​end 😏"],
"zcmchxw2gxlbincrchpdjopq":["craigweekend","It's The Weekend 😌"],
"siwzyrwlorgc3uxmu3kp2phs":["crumblinfool","S(even days a week) شیرین"],
"vsscixeyhqxrw7rdtlnbqhg6":["criticalweebtheory","CriticalWeebTheory"],
"3brnxa5g6gw76zqt5dwn3467":["crimsonweeb","Crimson Weeb"],
"akcwbtcorx3om37zrskn3ldv":["creadbrumbs","🥐wee"],
"y5c6fjqgxtu3edf4xaktnhbk":["cssquirrel","Kyle Weems"],
"4wcvznmioypmilolsmkbabig":["cumdumphole","🍑 ➡️ FTL/Pig Week Nov 29 — Dec 4"],
"mhbomnp7e3ggzhllyoht4r44":["darkroastweeb","DarkRoastWeeb(Ctonhunter)"],
"yftzyvrss3tp2inufnurga5o":["dandylyons","Some See a Weed"],
"2plf4adowk4r4exry6uyp2dr":["dataweekender","DataWeekender"],
"jv6phsprjkp26s45lcgsfheb":["darthweeder","🏴‍☠️ Darth Weeder 🏴‍☠️ 🌿🌵🍀🖕"],
"7popelvz5wgw5t7xzmwmzmp4":["dbmcweeberton","DB McWeeberton"],
"7u7pbtuxp7xj7kdt23hr573l":["deya","weed scared girltwink"],
"dfna72trtiuelmrt6kvccmur":["defox","DeCunt 🔜DoggyWeekend, Furcation, NFC #1944"],
"y774bytbe56hyqd44w2p3zx6":["death2weebs","120 FOV"],
"pjxmq5v6gyg3ovvbq3fxusfb":["denverweeks","Denver Weeks"],
"wfkwrymgyiyr72fn5nehe5rc":["deepweeb","Deep Weeb"],
"6cznpxm3cda3f7p3wgxs6ucx":["depressed-weeb","Depressed Weeb"],
"k65pney3ft244glwwgjhmvj6":["discomilf","Bonos wee crab eyes"],
"v3qeozk2kiemtwyzevvha5ab":["ditchweed","Weedy “Weedy Butterfly” Butterfly"],
"67ak4jbk5amgkdkkkbrqh5pj":["djweedpizza","DJ WEED PIZZA"],
"mrcqzle3rzeaz6bjbshjsspm":["djschoolpizza","DJ Chainsaw Man Was Good This Week"],
"drtr3evhy7kvynceo7is62sf":["dlweeks","DL Weeks"],
"ew6lzrpi6kszigjpq4w3hvjk":["dmchodge","Derek's Wee Toys"],
"4735t57ap4kuhrziue4v2rq3":["weedinventor","Andrew"],
"lnpkal7sd5de347mulhp3wfh":["drewmcweeny","DrewMcWeeny"],
"7dqkzhnjvhxthnojqwgmvj2h":["drknrdy.com","Drk Nrdy 🔜  Doggy Weekend"],
"jl6cossenosb5nklqs4qsutx":["drweevil","Dr. Weevil"],
"qbfnxdwhosqzl4cjg4ibooxr":["dumbweebcat","Dumb_weeb_cat"],
"m3ufqiimaaeugbbu7e7q4kyp":["dumteedum","Dumteedum - a weekly fan podcast about #TheArchers "],
"d4pjfx6ffloqzjcaivjy2vmg":["edweek","EdWeek"],
"ds7dvtohgbnvfzvwthyrycah":["egosumcassandra","Cassandra Weeps "],
"ryuse46j2sezw2ajapdiku4p":["eidolon621","danny weedburger "],
"456qvdyer5jl4b7feskx4bxa":["ellenweeren","Ellen Weeren"],
"sorx3cyfaz7rscq7yydxnzhb":["elisadeweerd","Elisa de Weerd"],
"iavgqwh56bqjp3j5q3n7ajyh":["emeraldshirefairy","Magic Weed Shire Fairy"],
"jzc4kk3zqpsa6y2xmi6cxynj":["endemar2011","Marinus 🤷‍♂️ weet het ook niet"],
"74ykkysufuhfnagzxyifzsen":["enbycos","Kes @ 👻 Anime Weekend Atlanta!🎃"],
"7gpaut53h2vlboqvrm6ayk3u":["ernaa-tweetje","Ernaaaa-t-weetje 🐕🇺🇦🐦🇺🇦🫂"],
"wrazq4gj3iy7t3wwk7ferqnb":["ericweeks","Eric Weeks"],
"6szkl2mkxkfyac766b3gbrny":["ethan4you","weeder griffin (scary) 🎃"],
"hj4gj7tq356ooibny4etikjh":["ethan.weecology.org","Ethan White"],
"skirvwkm53ehmtegq7i5h5jl":["etra.sh","Pup Rayne 🔜  Doggy Weekend | Furcation"],
"a75apvy5hf7r6d4xz5qt3vn7":["ethanweed","Ethan Weed"],
"abmidtdnefmpkla6g77f4c6w":["evemacgille","Weevil"],
"btsy5ijjcag7m4aplmammapq":["evieweeviewoo","EvieWeevieWoo"],
"57pc4p2ldeh2afbedypcluev":["extendoweasel","Weezer Afficianado"],
"v5yjfvcdys7hfh24dvnnzddx":["fallah","Happy Fallah-ween 🎃"],
"xwxaczejhm5ohpjlth3s6rti":["fatbearweek","Fat Bear Week (she/her/elle)"],
"y2ph72jnzt4v3w5uezjl3nn7":["fans4weed","fans4weed - grown up "],
"wneanm7fst5muegoibpxuhje":["fairuseweek","FairUseWeek"],
"5gbr27fas2bxtxaeipymkyrw":["femboyweedsmoke","WeedOfMia 🏳️‍⚧️🇩🇪"],
"2ajwur7tcb7vz25tptl3m4bi":["ferjeans","Fer Jeans | Fer Ween 🎃"],
"vreizuz4ye4lhcemgxx2ot2p":"fecund-weekend",
"hkfbrlshepppjjkbtyis5mp5":["fka2weeks","Souffle"],
"wp6gdbdk7ispm4m7icaoqupe":["flick","Flick 🏴󠁧󠁢󠁷󠁬󠁳󠁿 🔜 Doggy Weekend"],
"s7ztyjsqdftp2ma7sedalgdf":["flikq","Gavin Weeks"],
"rl6s3r2i3wqzuwg6mhpwtsan":["floozy","EP kent weed "],
"uxmbh4mzwv3im64iodvry5q3":["flightlessmilfs","ali-ween ! 🏳️‍⚧️"],
"omcy5ipzpu6jkar4nfgb7qwr":["floppy","Krill myself on live sea weed"],
"ilss4gmfxxfyllgqn7un3zph":["fluffyweetbix","FluffyWeetBix"],
"q34kbg3h6hsay53zez2xencc":["flemghazi","Weed Scholar"],
"vxvjr2tz24n2li5d2gsgg3cr":["folktaleweek","Folktale Week "],
"skpcykekmy3k7yhns46ifw4b":["frybird","Frybird - New Nightmares from a dying world, every weekday!"],
"wsnv73hmhxd6pkh3cfprknic":["francesweetman","Frances Weetman"],
"7ifv62y6gdvdvgu4p5li6hbp":["fredao","derFred_weeklyOSM"],
"enmmhloiyq6wvkgzujicxjtp":["f-type","Emile Weekers"],
"7ekpvrg7ne2oltxiiag4zcvo":["furryweekend.com","Furry Weekend Atlanta"],
"kguqycxcyv7jdvd4pxnhpnmh":["furryweekend","Furry Weekend Atlanta"],
"4emqdymcqil2uxj7egbqtv3g":["fuglyboi666","weezer"],
"mruz3mjptrngi2pxetpv75oz":["gabriellew.ee","Gabrielle Wee"],
"e2q74nceyjvdqvbf6z2swqki":["geraldine","weeewoo"],
"yltldu2cdwhbuw6znsonfirz":["gemjax","Gem o Ween"],
"qejws5hdmxnyhzg3i76gdjfj":["gebtdenhanffrei","#FreeTheWeed"],
"dpewy7kf4zg2cfjbgf4eamvr":["ggukphria","gi seven days a week"],
"fisbidmepsfpgau5xfva26uq":["gizmothevii","Gizmo The VII🩷💚: Glitterpup✨✨ 🔜 DoggyWeekend'23"],
"tcm62b74a2xjunxne5ddejj4":["glizzygladi8r","~King Wee Wee~"],
"yhn4nrd6jp7yh5k45ko3cubj":["gluee","wee"],
"vz6rncpzosmm6p6pn4lgtw3a":["gufei","weefe "],
"xojocvekufdek32qezqvcnka":["guusvw","Guus van Weelden"],
"75dkgvlry7j43jx2v3po7cax":["hawkinsweeks","David Hawkins-Weeks"],
"amit7bkpgp273tiip7yocvgx":["hall0weentwn","MAL (barbie (real))"],
"kf2y7eohui7m3u3577gc75yj":["hashjinnie","weedjin"],
"bvbpum5rqbvndinwuqgvwxs7":["happyweekends","happy weekends"],
"t3n64qtrjugfxamk76yyijqp":["happyweep","HappyWeep"],
"3kl3w66xl47afzwrfy2lmlzx":["hawtweelz","Hawt Weelz"],
"au352oy2kh5rg3w24xd4kevs":["hanneske76","Johan van Wees"],
"mcpj65txku4q3w6ymtbtkzze":["heshan","Heshan de Silva-Weeramuni"],
"b4qizg7hjn6cpfavn7lzjdqd":["headpatter","friendly neighborhood weeb 🏳️‍🌈🏳️‍⚧️"],
"5ijobeeunbfekdluxaq7ed5x":["hirabigdumb","weezer blue album"],
"etzhisayicclr6kv7w3jjetz":["highgrimace","Grimace Smoking Weed"],
"dd66fyomtqaohmbgsbrocmt6":["historisches","Historisches Sachbuch https://historisches-sachbuch.weebly.com"],
"4vfy5xazfsa62ov4xwwdk4rs":["holly-ween","Holly Ween "],
"sj6lnirxh3jrrwyaq33vd2lr":["houndsofdenial","weez"],
"fltg435jheib5ek63yf4ogab":["horsebitch","microsoft weed"],
"bmewhesbz5brlnbrgi7sca2s":["huxgrowl","Hux Growls 🔜  Doggy Weekend"],
"rxbdbvukeavrstdvadfdvzcu":["hukivulovic","Super Weenie Chud Giggly Goonior's"],
"bbg2kfjqoeldy26aoqgfudha":["hyunniefever","princess rennie weeniepup "],
"j6npucnvaojil5hxkn2lzcqs":["hybrasil","BobfattyOtrb❤️& friends. #Weetigang"],
"p2vowyggrz4fy5cdlvm7nolz":["iggypup","(っ◔◡◔)っ IggyPup 🔜 Doggy Weekend 2023"],
"ggcm2kapndhwkwgcw2yrqquk":["ileenieweenie","Ileenie Weenie"],
"p7nz62dg5rti5fabtnytaq63":["intenseweeaboo","IntenseWeeaboo"],
"ttykr24wwajzimwlmq42b3cy":["inkyquills","🪳 Roach, a dog but made of weed -🔞(N5FW)"],
"xt2c6dy4k3ih4qoga7pnhtj2":["inpupnitodog","Inpupnito is Small 🔜doggy weekend 23"],
"r6xuvhcujpyl2i4q6epacfs6":["insertanamehre","ʟᴀɴᴄᴇʀ' •DOONA Week•"],
"jfzrpe4lfha5woznrhrgdsmh":["ionlyplayasthe7","Wee I guess 🏳️‍⚧️"],
"rjcqo6bkgdrkneziupjty7xm":["irhottakes","Starfish who knows you’ll be back on Twitter in a week"],
"h44wdqvfobalgws6qxl3iy43":["isthisbloodweek","Is This Blood Week "],
"j5mbes4xzh4jiz223rp7cjo6":["itsben1week","my melancholy ass"],
"yc6kkp57jt4iyqffpryon462":["itisiweeg","Weeg"],
"mtis7kbugi6ygcqmb4w76zmt":["itsweezie","Weezie Proud Resister"],
"r62sgp3jtjvdy2yzun7n44t5":["jajcrob","paid the CIA $1,000,000 to kill a ferengi with a weedwhacker"],
"oveok6y5m6ahxieqlrajddnw":["jackieinertia","american weedass "],
"7y7tgjraxjuzgrutj5al4fwr":["jacobwayne","j_weez⚡️"],
"ghueqqmcfym7rrv3fmbrelqx":["jamie.wee.codes","Jamie"],
"l2rjn5mtnwndt7o74fdquuch":["jamieblair","Wee Cooper"],
"tchfcse2hdowrw34md3clmgi":["japanweekend","Japan Weekend"],
"nxhgt2jp7sks3d2su6p6nul2":["jdgunderson","JD “Weezer Goth” Gunderson"],
"7kckw55lqgtzcgecd2lok6qt":["jellymoonvt","Jelly🌒👁️Freak of the Week"],
"sk7lz6owqtk3o76w3ofpdgoc":["jetzeroinfinity","Jetzero Infinity @ Snobby Black Weeb"],
"zed4qcoeavu6txdv2q3a4eds":["jevthefox","Jev 🔜 Doggy Weekend, Furcation#447"],
"abzsqukwyahkxbifihi6rn43":["jenniferweeks83","Jennifer Weeks"],
"aicn5guls2cax2imtbai6iie":["jedweeks","Jed Weeks"],
"ppu6aw34hwoovn3oaq3l4ose":["jfweehawken","JF Weehawken "],
"j6qup2esgd5jr3cgnokhrerc":["jimsonweed","JimsonWeed"],
"qzf45sqvi3zejjv5rlaadgnj":["jkholland","Jeff HolloWEEEEEEN"],
"2byzrpskkki6j3io7kuq6l4i":["johnweeks","John Weeks"],
"o73pvtz7zolreb3kx26yxa3h":["joostdejong2","Weervolger "],
"4idso6m5onjm4rkk3d67cmvo":["jolynekujo","Jolyne Weekly"],
"swpsg3jw6o3gcxsn3hddckjr":["joelvdweele","Joel van der Weele"],
"pgq5lmxdpynhxhdpbasnoemv":["johannsalpenweer","Johanns (Alpen) weer"],
"bqoiedrqox2bgybe3is235uf":["jowe69","Johan WeeTom - Erlandsson "],
"27ofkiutsbfsdtr74pugjpji":["jspin","Weef"],
"xwtzyp4izgrqqazno6ktj4u4":["juese","Juese [Wee-s]"],
"5pwg6b4ljdcmqtp7gca3g64d":["justalncase","Justa They just made mery week real check it out "],
"biwho3jlji2pw2usnn67mwca":["k0ko","A Weekend at Pete Rose’s"],
"pmwphri5ja62ebgwrs4t7dr2":["kalikoseaotter","🍀Weed ⚡Pikachu 🐾"],
"jkcwgk4uwfv2n2gyt645q2ur":["katieweekley","Katie Weekley"],
"bkkuv7crkipwctc27ith44ro":["kaiwithpaws","Kaidrin 💚 @DoggyWeekend"],
"7qzuvztm7cxil5hgi5vbzmpj":["kaicarlsonwee","Kai Carlson-Wee"],
"udgjwxm6iota74gwkplpxmlu":["kasja","Kasja Weenink "],
"jt6s33zird6vwvdpd4n34nuv":["katweegee","weegee"],
"zyg3a3cmo7jpg6ubq443h44j":["kbuts","Hal O'Ween"],
"ubmlspxnks2b4gx5a5smdkwj":["kentaenoshima","Weed King | Enoshima - San"],
"qikyah5ueg75cpongj7aozd5":["kelseyweekman","kelsey weekman"],
"7jvxyin56hut4tsi7bq3ywom":["kelcaine","Kel Caine 💓North Surrey Incall💓FMTY Weekends✈️"],
"pjotm7aoqwivjym4zxbofbyf":["kipkap.dog","Kipkap➡️DoggyWeekend"],
"fwzr2pamtcrlmv6to5ilkc64":["kinkphos","Phos ➡️ Doggy Weekend"],
"hla3gkksmtwpbatkzpj5ko4d":["kittanzero","PITA @ 🦊💀 WEEK NOV.5-11"],
"tjdbxk4s6cvvxqzefqtkuts5":["kijou","Kijou - Milan GamesWeek "],
"ebefa6connng43xlgj4lcfbp":["kirtfox","Kirt Fox (2Weebs1Dungeon)"],
"q3qxyye7gke63fjqtor6hdi7":["kmleiffel","Kml ✈️ Brussels bear week"],
"ktcjn2zogqhktcmf74dlx2ry":["willowweeper","willow weeper"],
"xu2hs7b4zcyk6jedp3xohhpi":["kowbayashi","Wee Moo🏳️‍🌈🏳️‍⚧️"],
"2j244gxfgleeadbjfpemyvvt":["koopyrose","wee koopy 💀🎃"],
"iu4m633kqlovy4i3d5q5ftxu":["krisswee","Kriss Wee"],
"gjgmvnc3e3jrmtnnwymvn5wj":["ktdk-weeb","Weeb-Sinna 💜"],
"cs63iedz63u6bqf6rqqog5cv":["kuyaeifanweek","Kuyaei Fan Week"],
"mye6hj3h4g3jva4t6socdzfb":["kweeda","Karen Weeda"],
"2wy4f7tds4kl7hwnfts5fua2":["l0u13","lou weed | Still the President of the Mia Goth Fan Club"],
"3cl6h6pe6fw6pcfqr7fr3nui":["lad","Wee Lad"],
"263kl6roruhxc5xax5qfvnyf":["larrythepotoo","🏳️‍⚧️Larry:alt-mode is weed"],
"y2uxlduhcdstnrdouru75kcs":["lakes0644","Darrin Weeks "],
"lkmunwvme3gztmputvavrena":["larryweese","Larry Weese"],
"abty5hpy4wjcf3zxw3r4buup":["laboure","weekly showgirl jump"],
"sm7jjs7tjezbfgpuylg5yajq":["lastweektonight1","Last Week Tonight with John Oliver UPDATE"],
"5nxs4r4dyo36ztlaoks52wva":["lesserof2weevils","James Bickerstaff "],
"zfpy7wnvgvn5z7czkwjgynr5":["libraryskunk","Better Weezer"],
"ijc7hzjylcv76q4ovu45ori6":["lilachysteria","molly the weenie man"],
"manmibxz2evx3kt75tcvynw4":["lilyspun","weenwoon ♡"],
"ud4427kcpyih4w5ive4c7ub4":["littlestgiant92","Terrin Weeks"],
"dosysoj7g4nxrei4jgt5c53c":["limeblood","oh ween"],
"6fzzjrtopckxntjugwkwtkqe":["lisaweeillustrator","Lisa Wee Illustrator"],
"jz4rtl6znlk2rlika565zi35":["louosaurusrex","Hall-Lou-Ween 🎃💀"],
"azdkfdei23mt2chgkryaa2fc":["loudstrife","Skateboarding Weed Dog"],
"res6mdqqmfsldxorkcxxcgkd":["lookoutscience","Avery: Weeb Physicist 🏳️‍⚧️"],
"cf6gp5p2o72v4ptmi3clpsan":["louloubeaned","Elle-o-ween Memory"],
"ovezcega3k3ojfjguodmfbqp":["luigisbrother","Loogi/Weegee"],
"fgc7dlmdtn2yodmcf54nc5ey":["lucentweep","Weep, in the psykaeyatrist ward"],
"kqpy35m3f6vmb2td6zna53dz":["maddyweeks","Maddy Weeks"],
"uoy2mhdy6qwpscwcws5b5ydh":["weekbladmare","Mare"],
"krhqrwecrjdhrcxipcjeijgt":["maggotwormz","little freak of the week | mike🩸🌻| 📹💒"],
"7gs2y67gbpqwmwnzmwogryrs":["masterq","Quentin Weed"],
"xr57663agvg6vdrch6r4h6gl":["mattweers","Matt Weers "],
"bd3slzeorapkjlosxpzwx65j":["makoto-niijima","Makoto Niijima Week || 新島真 "],
"qmcwadezywp4horm7d5qwb3v":["memesterotwpod","Memester Of The Week"],
"4eqej5ftm3yqigxtawgdyhqr":["meawch","Alicia — Degenerate weeb"],
"vrmgl6eizc4cuengeslnlckp":["mialeesakura","TOTAL WEEB🤣🤣🤣~ sometimes 🔁/❤️ 18+"],
"7dubdd2akhpfvojeqqp5kldi":["michielvanweele","Michiel van Weele"],
"633ecrufx34mxjomdimx5gfy":["minachi","🦇 MinaWeen 🎃"],
"xyqitxhl6jv3n3jnspcok6er":["mirko685","Mirko Weege"],
"w2xfw2xgazvte2ox3crzga34":["mjweerts","MJ Weerts"],
"w67chdjnncdly4vmyvyzf4li":["mmorgann","Weeb Foe"],
"7wiwdxr7ia27iaoq4lkywfor":["mowgzilla","Wee Mowgz"],
"v7akpieitc62vpljeft6yjot":["mochiicupcakez","🌸~Your Local Weeb Senpai~🌸"],
"vs5uvelzwsp5ezd5rmqsy2fg":["moontheweeaboo","MoonTheWeeaboo"],
"nvfeyjgkbibtd4scr6cvlcns":["monsteroftheweek","Monster of the Week"],
"jfxt7cdzj3q5qecfmehfip3d":["moniqueweemstra","Monique WeemStar"],
"rvejxbmvxdjn24bk5gww366b":["monolithweekly","Monolith Weekly"],
"x6vwzckpwcedujx6oo7yku3f":["mooninthewell","Boe (Pronounced Bow - wee)"],
"fyn67d7kab4kdvll5qp6oyu5":["mrteenyweeny","Mr. TeenyWeeny"],
"oip3utfhy5324kb46qntofrq":["mrweegee","MrWeegee"],
"j533skick6ctb734doj3aaa6":["mrswee","mrs wee"],
"jyy2raryvlpi3iyotojgyuad":["mweeks.dev","Matthew Weeks"],
"3xzjap62gnqz5fa5xrcej2sv":["myweeklymixtape","My Weekly Mixtape: A Playlist Curation Podcast"],
"aa3jxwhtwudbip5cuxpgeesd":["naweed","NaWeed"],
"gkns6sfigpsccsmyq7f6lmmc":["naughtybear","NaughtyBear🔜LeipzigBearWeekend"],
"maje6k6yowpu7smm3f3vx4uw":["nameless-weevil","Micheál"],
"25kjdriusxokmi6lrwhs2ogp":["weepy","ne"],
"4f23fdoaety6vojxo2pyh3qz":["newtoweeaboo","New To Weeaboo"],
"lyymtdxqrjqp2oygwixsfr3h":["niceweeb","Nais Weeb"],
"7ny6r2jkzgpw5stn7trrqxvz":["nicholas-weers","Nick_W"],
"kvmj3ox47frcq6pkcki7jy6f":["nonameweeebu","NO NAME WEEB "],
"64zisxu557sj6i5bq2xgftw6":["northishorganics","Weed Grump"],
"gqzwaw76bibjtdwfby4pkc5l":["nsfwkyluxweek","NSFW-Kylux-Week"],
"s44qwjl2m3khlvzllewn5trs":["okstray","weedsky 🍃"],
"ufxyq5jm5qtpmy44hplych46":["okaeribkdk","Okaeri - A Domestic BkDk Week "],
"ddjmynfybw4cohcuv3dnt32p":["olliweeer","OlliWeeer"],
"gq2mqkwhj6zhe3sogfkrzniq":["oneweekfreetrial","OneWeekFreeTrial"],
"cjuyuk7fprtj5lqoggv6vgsc":["onlyfans.pictures","Weed"],
"qndudpbziys5je4jp7ehhbug":["onefussyone","Weegie"],
"ebujqjax53hjhklkyn22dsys":["onceuponaweeny","WEENY"],
"urimryqw4u6jsf5pfqdgr4hv":["otto-weeka","Otto von Weeka"],
"l3fyst5i24nlat4ie2hgavho":["oyasumination","say your fucking prayers weezer"],
"bcezqcril5leem2stbvsezni":["palmgeese","Ween Hackman"],
"wz73thcpowsfeoykwuez3jhq":["paulweedon","Paul Weedon"],
"3aw2scbxf4h5sjqbwxgdxqc4":["paperbirds","easily onward, through flowers and weed"],
"7sd5mx4nhepw6bz75cnp524h":["patrickweedmob","PatrickWeedmob 🥦 🍄 "],
"7u7nb2ji4dulrx4s3xpptrlf":["paperweegy","PaperWeegy"],
"qt4nwzgtkljunt5x6hqa7ojq":["pandareddy","Lute's Weed"],
"rqi57pdkegudotn5y5ahhmgc":["peteyo","king weed king"],
"en7i4w3fdgrbmldbf3dq33yl":["peewee1976","PeeWee"],
"hcnvst7xafqxb3kwu7im5y5u":["pitredish","Weekly Newsletter"],
"gz6bz3ehaqwqcvsfdqfrwmqq":["porucrobun","Poru🔞🏳️‍🌈 (Black Furry Weeb Gay) 🐊🐰"],
"6675wh5oclrmtwdogr34vkgn":["postalspeedweed","Postal Speed Weed"],
"ma2tqivw5iliddpki3conoax":["podskeeweewee","Podskee Wee Wee"],
"ej6lnninbm4przvok4tjiplq":["powerbiweekly.endj.in","Power BI Weekly"],
"xm5c3xvas3hl4kc2wt2rm23a":["princesmweekes","Princess Weekes"],
"l2lznr4wuxfhodimnz4b4sjb":["pray4weebs","pray4weebs"],
"wijj5a6wwxzc6wi3wrxgyemp":["prinaevergarden","Prina Queena da Weeda"],
"ig65zp47fuetouc6bfv3nhxk":["prokaryoteszn","weebo⚠️"],
"vowftco57xqyby4ssosqbdc4":["presumablyweeze","Weeze || ウィーズ ☁️"],
"c6ac4zhf2hqt3krhmspemgzg":["pupsora1","Pup Sora ➡️ Maryland Leather Weekend 2-5 Nov"],
"he6ko242ut446httercxhsj4":["pupnerdy.com","Pup Nerdy 🔜  Doggy Weekend."],
"ntt5uvsjoyv23eihww552e2v":["pupfrost","Pup Frost 🔜 Doggy Weekend"],
"rhfzqveb2luo73ihihccyua6":["pupstrelka","Strelka - The goodest boy! 🔜 DoggyWeekend"],
"5xt4tcev6qnpdf6q2hopf7ue":["punmutt","🌈🐾 Shibe-Weeb "],
"dx4tfirs2ql3ygwyc6nuvwhx":["puparchie","Pup Archie 🔜 Doggy Weekend"],
"wfmcazd64w2ipocmh2qdhjqg":["pupredfire","Pup Redfire ➡️ Doggy Weekend"],
"q5zfaian2hyejglcamzd5v4y":["pupchas","Chas 🔜 Doggy Weekend🐾🐾🐾"],
"5liztz7ckmkzy3qr64x62yx2":["purpleweedygit","PurpleWeedyGit"],
"fqu4r5e2ubkuta6umx5ydqm6":["puprufusad","PupRufus (mostly harmless) 👉 DoggyWeekend MCR"],
"w6oz3pgneslsdi7pinrovzqf":["pupjayjay","Pup Jayjay --> Doggie Weekend 🐶"],
"lg7g26i7ctqgwanh7ba5p2bw":["puprogg","Pup Rogg @ Doggy Weekend"],
"g2abamntzxx7k5ppuflvqbwv":["qijiuweek","QiJiu Week"],
"iexvullzyc4bdaer35rwevw4":["rachelweeks","Rachel Weeks"],
"tbgeoyawbcbepjvtdte47ee7":["rat2weed","jackson :3"],
"zi2nk2xb6dlah3smwwkoj52t":["rbrwrestling","RBR: Weekly Wrestling Talk"],
"yafuvwclr6dud3r5yiqpxtw2":["rensstudios","✨Weed!Dad🔜FM"],
"whnfuzrvijylt64m6gnliaoc":["retsujo","Weeb ankou"],
"wrjshzfz7b76gjngkafb5254":["rebornweeb","RebornWeeb 🦨💨 Spotted Skunk VTuber "],
"i776jk6ymxx7sqsy2zqllc4l":["readitandweep","Read It and Weep 📚"],
"lzbfeeelz22tmu36jj3evhrv":["rinharuweek","RinHaru Week 🌸 2023"],
"e526lk3xlwe3gwvnoecpy7zg":["rilureddu","Weewoo"],
"udz3et26ycttukkq3ii2iex6":["riaweerdmeester","Ria Weerdmeester"],
"5fpykjxwewly4pik2vxpqmhd":["rkrentzwee","Rebecca Krentz-Wee"],
"3i5sfhfdzrtia4vcuhhf7kbp":["thecomelyalpaca","Weevil Babe"],
"wu7whr4qnnksctcabwcy4ykx":["rologica","Rogier Weenen"],
"d7ub4omhrzsc5kalikzrvt3f":["robbiedesj","Robbie Ween"],
"daffdn2h3f7wb7ywvsrjuj2w":["roelweerheijm","Roel Weerheijm"],
"klyehbgc3pyyqzqzqwe44jyi":["roycemillerwrites","Royce O'Ween"],
"7iukuqi7e4af55wdjnovftze":["rumweed","The Rumor Weed"],
"wgb7swj5oah6kokjus24syoj":["rusticraver","Cave Dave and the Speed Weeds"],
"4gkg3w6nbgm53n4olrpj6kgy":["ryanweeds","RyanWeeds"],
"yxoqebxaw2jppull7rumnul4":["saffronriser","Patroclus Weeb"],
"kxkj5n4a7ir3kvkdd3scm3x3":["sadgirlweekend.com","sadgirl weekend"],
"v62wkgaewjq5nnvllms5i3sh":["sarahdeweerdt","Sarah DeWeerdt"],
"w2c3g233jogkfbcqvaou4mwy":["sangchengweek","SangCheng Week"],
"q6flz43hfolafqbxxp3tlsyw":["saladween","salad \"weenboi69420\" robertson"],
"4utunam3p5vvizgacyfsiqnl":["sarahjennings","Wee jigglypoof"],
"ameptychlxxyzxl7fn3xirvj":["sajilicious","Saji Weerasingham"],
"3vb326waxpfp5sknzaxgfq7s":["sadtree","Weeping Willow"],
"6sgdn74asj4fzzc77i6vc4zx":["salweezer","Sal Weezer 🎭 "],
"hk7uoyvfuuru4abb2xl7adve":["schweizercomics","Chris Schweizer (at Chatanooga Comic Con this weekend)"],
"vlsafpxgt2txvxavo7yy3fab":["scotty","Scotty Weeks"],
"cttplrwp7nyccjno4vh4p4ry":["scotus","Weed"],
"oxjyqteota7asv7v5lwuqeu2":["scriptjunkie","Matt Weeks"],
"527decg37xk447rjllc7nr3v":["scottishpuplevi","🏴󠁧󠁢󠁳󠁣󠁴󠁿 Pup Levi 🏳️‍🌈 🔜 DoggyWeekend"],
"hsi3hlywrq5ly6k2bp23dbb4":["scritch","Scritch 🔜 Doggy Weekend 2023"],
"cakxwr7lj7oldgsqs47wkk5o":["scallyazza","ScallyAzza 🔜 SneaX Weekend (Nov)"],
"l7f4dgf3ho56l7robiqnhpff":["scrogchief","Weed"],
"5d6wpsoyhgtr6csxly2t5doe":["sennydreadful","Jen ‘Hallowed be thy ween’ Williams"],
"6rh4jxqpmszfmwdrdz4c5tdb":["serafina2k","Tiffany Wee "],
"qblklhjyz4m5wfsgpdvrsviv":["seppukudoge","Kenze Wee"],
"3hkkbjtarzpkiv6onrmf5mpb":["seppytheseal","🔞Seppy The Seal | (They/Them) | Local Weediatician🌿"],
"4x5gtzzyhswlnr23coiighez":["serenlyss","Lyssa @ Ikesoren Week"],
"jagjehny6o42u3xwho3xna7x":["shrimptimes","weezy"],
"ovoleh23dhzwoq44k6ubjrmv":["sheltonweech","Shelton Weech"],
"4vjwu66k5c4zck74awxymaru":["shween","sh weenn "],
"lzjex3tb6tonpnkqxaw6k3by":["shinzawaweek","Shinzawa Week"],
"tuhbqfnhmvwdeyz7xfamvaoe":["shitpostj0nge","❁❁❁ $weezy ❁❁❁"],
"dotefcpzdt2wzafnjdseyqtg":["sillyandmorbid","if you see me, weep"],
"divheedbimzgdomjkup3bl4u":["silentrequiem","Silent Requiem 💧 Gently Weeps"],
"fxvuhqr7pravclefqtjlc3r5":["silentwave","Queenie Weenie"],
"wbxcqnq45o3r3iumnmpt2y65":["sidehomie","weenie"],
"lmqzph5sf7j4qwi3x75hevoc":"simply-a-weeb",
"cf77wdfanl6loplgy7tuiphm":["sluggoislit","Sluggo if he smoked weed"],
"geeqlolnqc2n2bkwzwvruhgs":["slyweeklie","SlyWeeklie"],
"m3z5nxhf3vaketzuoeesvyes":["sleepweed","Eep Weed 🧸💤"],
"qi32bf7tbbcw73ucp6zgw5cq":["slutweed","as far as i'm concerned all weed is slut weed"],
"msywts2bgnre5mfq3mjucbxz":["smolweeb","smol weeb"],
"52kyprsuivasf3abo3ioyejn":["snugbugs","weeeeeeee wooooooo"],
"tntnduesc2bnfuoktnemzfy7":["sockflintheart","Weed wizard"],
"gk22mfwtho223kfza4tstrqg":["soweerts","Sophie Weerts"],
"3vprzxozluwffdw5myyfhrtz":["softcockweek","#SoftCockWeek"],
"heb66xilcxfl254pmrofvwmo":["southsideweekly","South Side Weekly"],
"5bsqvpz7ehpp4jv37hjqa5ws":["sombra.weebs.fr","P1ng3x Fan Account"],
"5qxrbubnhr4retqk7gomfczh":["soupnbooks","Weed&Soup&Books☭📚💚🍲"],
"rrczy4exs7jt6h7pjuz26zqc":["spectrum36","weed shark "],
"kzivpq7emxkeeq5cl4ybj33n":["ssj3goku90","The Weeniest YO HO HOI 🏳️‍🌈"],
"f3qyhpjsma3tmil23gnbmtel":["ssjlayne","Weezer-kun"],
"5vaihlwg7isazy66ar6ujt3b":["stopcopcity","Defend the Weelaunee Forest"],
"sp3xx4na4hd7wjhehzy36pii":["stellarsoph","the grim weeper"],
"gv43whgbun4olkzxkkbfe2zj":["starweevil","StarWeevil"],
"5iyxwxgv6turmjktslxs4jcg":["stahlmf","WeedtaminC"],
"qlvzkm3izwwpzv3hhatk3y4r":["streamyweemy","StreamyWeemy"],
"ss74mzedtcga6u2lpe4tim7u":["strayowlbear","Weeping_Jay"],
"vfaqj2ers455whxfal2fyftk":["stillnoatyet","Weegee-man/Society"],
"daghercb63iromowh2pawldd":["stickiestboy","Hallowed Ween"],
"y6hrucc47xc3p5yqi65tex3u":["stardogweekend","Stardog Weekend"],
"nkxdto2gebkz6ozf6ev6jdzx":["stelloli","🐾Weeb🧋Stella🐾 ENVTuber "],
"lmibe3gndx25jwssesslagib":["stuartweeks8","Stuart Weeks "],
"zy53jy7h6rk6n6wcby37qxfr":["super-weenie","Erin Price"],
"yo3nyprp4jiwyuafa526ujoj":["subzach","Pup Zach 🔜 DoggyWeekend"],
"sdqy7nc57fcl7v5hu47nglar":["sumi0510","Weeeeee"],
"qg5bndla55kc6usc6ry4u52i":["sunflowerweeds","🌻sunflower weeds reads 📔"],
"dpbr2agja3mpao5wbxzk3luf":["sunnywee","Sunny Wee"],
"ydqle5poj6mcd7ig5ycfb4dm":["superstevie268","Wee Stevie C"],
"zc4tr7cvxzuotj666wmkk2yx":["superweebbros","Super Weeb Bros"],
"42aecmoc7tezxyypup5dhyqc":["switchweekly","Switch Weekly 🗓️🎮"],
"swsahmdm55gmvrddxje5xtkd":["sweeks","Shannon Weeks"],
"fdceevg5tqjdms2mvdl7l7oj":["sweetgenealogy","Stephanie Kolonko-Weet"],
"blnjxyxvci5kxbfsi3qh5q4z":["swimwiki2001","Swim-o-Ween"],
"ligxfpvbhhjnltpvpskmfp4y":["sweetchiz05","sWeetchiZ05"],
"dhm26gybij4ry6d226gcgrlf":["sydweedon","Syd Weedon"],
"oavtl7zgtcfqhwq6xsktmpkz":["tarheelphan","Brett Weed"],
"qlgz7owgokiuzahbbf3bnrya":["tankasaur","ween⚡"],
"ffczm3ggwrx3mtgjdfryjqz7":["taws","TETR.IO Amateur Weeklies"],
"bwmvahlw7kcetai4juyjb2at":["thatweekinsnl","That Week In SNL"],
"lhmds274k5xi2kiqtt2wiv4g":["theweeklyscroll","The Weekly Scroll"],
"sk3xanifl5g5skl226umfpi4":["theweeowl","The Wee Owl Studio"],
"lose2lvk7j4nsf54alzkdn3c":["theweeklybuild.com","The Weekly Build"],
"a3xu6zdjb6flccxtz2b23l2t":["thisweekinhs","This Week in Hearthstone"],
"sidkxra334yn3j5xcodnxz77":["theweeghosties.com","The Wee Ghostie Company"],
"6tykxgnt3yf2jxo34fjfkwci":["theweedout","the weedout"],
"xgnhhsrkiwwlwsuhgvqofpu6":["theweepingdalek","TheWeepingDalek"],
"sdhpaevkne7pvl2s6zwlbuuk":["thestonemarten","Here Weed Go Again "],
"jh6p3mrzfzojauyohd5q3in6":["thisweekinaurebesh","Intisar - This Week in Aurebesh"],
"siey6vypvfz4un7jwotya76c":["thclovebuck","Eros,theWeedPup/Buck"],
"3elricpm2aoal6tmepgcwrjl":["thefandomhopper","🩷CEO of loving something new every week 🩷"],
"zf25pmbu3op2lv3csplytvky":["thyweepingwillow","Thy Weeping Willow"],
"jgz4lvz6wr6bgcbhp25gokf3":["thirdimpactanime","Third Impact Anime @ Anime Weekend Atlanta"],
"427u5vx55i2xqtwd4qoc6fa3":["theweebee","TheWeeBee"],
"2s6qfpdjlgsrtuvnlnnnej7t":["thosepastelbun","OtakuWeeb"],
"5lo2vah6j3eegd4bw2ipge3k":["thetealord","James 🏳️‍🌈🏳️‍⚧️ Two weeks to Germany!"],
"kkylkvyhm6x45thlrhcebo2m":["thatrandomweeb","That Random Weeb"],
"4s2u3bfgl2kodnzpvhbxaxqk":["th0m099","Pup_Thomo_99🔜 Doggy weekend "],
"66msx2zqisue4rhtul4ikiev":["theawkwardweeb","TheAwkwardWeeb"],
"os74lytndtb2ukbkkaenjtcv":["thijsweenk","Thijs Weenk"],
"q2dssy7ub33wrk7ptrbj4x43":["thorstennesch","Thorsten Nesch - Sci-fi weekly"],
"yksvc6gz3fluretf2bbrucrt":["thefurryweeb","weeb"],
"boomq3z6bjlxuitwj435q42g":["thedragonlady13","Riley Weeks"],
"b7bgchosykinovmdhs6kypzy":["thedigitalweeb","TheDigitalWeeb"],
"2nevg3fjjwttuox5swrdceen":["thegospelofweeb","The Gospel Of Weeb"],
"wjtr3pvt4txq2x5kds45zlg7":["theatreweekly","Theatre Weekly"],
"ob6y4ma7uund5565mqkl26me":["thisweekinlinux","This Week in Linux"],
"l4bfz7lkmmldc3u3aetsw2lq":["thebri04","spooky_weeblet2023🎃"],
"wybgod5yd2qai3nhanunoz77":["theslaywrights","The Slaywrights - a weekly DnD 5e Liveplay Podcast"],
"yrt4gev72ijuszfbqfiymc4r":["the-weeb-boi","Weeb boi"],
"z3qfcv4qpbrhlfhgzchzg6m5":["timecompactor","tyler presents ✨grinch-a-ween✨"],
"k7upyggzbm5lomwmbyyk56us":["tienacg3h8weet","Teenage Witch🧙‍♀️"],
"rctgfhv3o7mlckqupjdsaicw":["touchscreenpenpal","weekend nachos"],
"uxgb7ljdpftsqmy4wmcdqhwf":["tommcweeney","Tom McWeeney"],
"2znkikj4whfsfygetsubw2xr":["trickweekes","Patrick Weekes"],
"gqzy7qdoox4lxxsy5zfcfek7":["tracyweensmith","Tracy Ween Smith"],
"mumtq6a52ks3xitz4qtkyyuj":["trewatsonmusic","Tre Watson, Weeb Music Overlord"],
"mohzihxauekme3tiiyrijutf":["transterrorweek","trans terror week (nov 19-25!)"],
"wfuqq5z5qzebqimlpjrhxwdv":["trollipolly","That Weeb Girl 🌈🍄🎃"],
"cnpiketfuus2b4zynmut6r27":["twinktyro","Tyro 🔜 DoggyWeekend "],
"pjmkjsfmjtj4qb2d4ktzdbaj":["twibhistory","This Week In Baseball History"],
"x363b6gs4l7w77myaw6sybps":["two-bit-socrates","Weed Thoughts from my navel"],
"v5nveob6kufzfcjzwhw4fpml":["tyden","#TYDEN / #WEEKLY"],
"juapace4dgaxaxicrqa3l5yt":["ugliestweenie","Ugliest Weenie"],
"4y46kyk5od7s6rg54puodo2n":["ultreece","weece"],
"hdxqu7prk45w6yegonocge72":["usumcasane","Trevor Weede"],
"mevq7mbjwrjk4nywrnhf5bsx":["venusweenus","Venus Weenus"],
"pz42l466imljjtx2k3w4dqzf":["vgweeb","Plant Based Weeb"],
"zutbyk2riaiszvf2vuksojkg":["virgil","weep"],
"w3ya35f53wwbwlt2dlzhjlhx":["viocrence","Señor Weenie"],
"owz5vzlb4xdhwuzha7ckpfk2":["voolala","Moll-o-ween 🎃"],
"dxkzdscvzknxnubjwvrkgasp":["vvapourstruck","🌈Certified Weenie🌈"],
"btbgqn2vjfxmqpxrzxmn7idt":["w33bie-0","WEEBIE"],
"ns6tatr3arzwv2ygfp3k4mf2":["wannlegal","WEEEEEED"],
"p6y4pc6ztlnilsffazym3qtu":["wamaweeber","Weebery"],
"2jaajua5oxc7tlnp476faysn":["weeble","Annette"],
"2uwkjukamqkxnztrxvs3ozcw":["weenietowne","Laura Verdin"],
"2vimsxg2zuzr22w4tif4chi3":["weedguy","Weed"],
"34q263asqvu5hschnuaq5dqe":"weedramatic",
"36gglshijx53pfqx6gkyk32t":["weekendpoetry","• Weekend Poetry •"],
"4bjc5l6sxponnniceccnyyjx":["weeblewobbles","Morgan Pasquier"],
"547xsifmpb4rdfdxozkxtzg7":["weekendwolf","WeekendWolf"],
"5i57jes3dfmgcs773mdly7tr":["weedhitter.shellcorp.net","levar burzum"],
"6ck2mfqdsj3ihdlwlb6g6ewr":["weeklyreader","✨Reader Librarian ✨🍁🎃🧚"],
"6ixhocm5tk3fsqbclrbq36mf":["weeder","weeder"],
"7kuutlx2fpr76qb3e5n2uum5":["weezer","gwendolyn"],
"7xcvgxjovnuzvhhoqamqy5cn":["weegiegraeme","Dr Graeme Millen"],
"adny5lc25k3vwkrp2gn5orgu":["weedsmoker.gay","Rat 🏳️‍⚧️ birfday countdown 8 days 🎂"],
"aooqn44nfwp5fotel56q7uc3":["weekenddad","Weekend Dad"],
"bvapd5ugyahbgu5zab3zjvtq":["weedlejuice","tara "],
"cql5xqhqzl5pwnc7k3c4j4dr":["weekly-utaran.net","歌らん(平凡な一般人)"],
"d5wzr5qmotr2g5gca2b4gjgq":["weepyluna","Audrey "],
"dfxeuf7iz7ycoa3pixlediwa":["weekend-hippy","Weekend Hippy"],
"dyfn2qcui3vjfmh3mg5mst3h":["weepingcheeto","Trouser Snake Plissken"],
"e47jum7sbu7ntmt6hxplye4g":["weedmasterlab","🌱"],
"enz25uhbanarja6nqkhioczx":["weemancom","Chúnna Fiagaísaol 🅾️"],
"fewiow3oulnmlfjaxwquk6ah":["weeshtable","Weeshtable"],
"fmjo3shi2enqi6aji2hnbzdw":["weel","Coba Weel"],
"fse42iv47meacovacut2kzyo":["weegeecool","WeegeeCool"],
"htkwuquc36piovfx5b7riqsh":["weebslayer","Hessam"],
"hwmmhlgrrzfb2hmwbgbxv4za":["weesjebestezelf","Ingrid"],
"i5lzslxhmhymft4rnfqqdrmp":["weequipped","Alexa "],
"idmwkzyl6hcbf6dgwncx7vhq":["weevilyn","evil weevil"],
"j7eze3gs6r2rg7xkwwxblsvs":"weedspagon",
"k733ho42hqkv44xzeehmmqvq":["weep.jp","weepjp"],
"kjue4yke2nhvw4xorowdzwii":["weedshrek","touch grass"],
"lqk6saipiyjn34wjgt3mtfek":["weedlord","Sino Soviet Spliff"],
"luvom4kxa2uukokimsvl23b3":["weekendfisherman","週末漁師"],
"n632ttk2tmtkwk22muxiriap":["weedwolf.gay","𝔚𝔬𝔩𝔣"],
"nnw5pihg4a7xk53bn7toszni":["weedcat","Weedcat"],
"nyymr44kstrynsir5f7ibgc7":["weeknightwriters","Weeknight Writers"],
"opckra7ageynmkq7p2jf3wbw":["weeter","Weeter Wolf"],
"os3qjyoefpxtkx7icny3n4zw":"weedfreddy",
"pjcldbykpkzjg44q343ok467":["weedwizard","The Wizard, Weed of Canadia "],
"qldrnsjewtpl7nkqpfrjaqmv":["weedlawyer","Gail Brashers-Krug "],
"r2eeemq6grdavcrjiez7njl5":["weedle","Weedle"],
"r445gtomamrx6litgcxdubmv":["weezykid","Louise"],
"r75jnrlmmudbrrzkuhhuvprg":["weenatalia","Natália "],
"rkvdybwpv36l4yjqetzlehtp":["weeeee1232","랭"],
"rlvmj4vlywerq6mr5y7krfep":["weelittleladybug","Jae- Wee Little Ladybug 🇰🇷🇺🇸"],
"rmktmdr65ewoeinur2bfnyih":["week4paug.net","week4paug"],
"rr7gcfunubs3uefb5ocr3qju":["weener","Rachel"],
"s57f4oree2omulko76r2fkek":["weevilmeat","remy 🔞"],
"sfd6k7tulepbgcawcblmfaat":["weekend2023","2023"],
"sjzzngsj2pdvllak4uyrny3y":["weebitsarcastic","WeeBitSarcastic"],
"t7wubtq5yhdtvtlzjddiqydp":["weedpixie","Punch Local Nazis"],
"tbbwsqrd3lvsocuhcy2a5wcp":["weemoxy","Wee Moxy "],
"uhyujbbuwbhr2mmro2d55e2b":["weedlordbonerchamp.hellthread.vet","Weedlord Bonerchamp (He/They)"],
"uta7zcsp5g63uhiatjayesly":["weebzee","Weebzee"],
"uywraohh6h65gpv3w7fbtqao":["weems","Weems at bsky"],
"vezvdmidyzefmsowhcqqcqjx":["weedenkim","Kim Weeden"],
"vmq6pfs7d3t2oxvp4ghhoixy":"weed.sex",
"wk5xkjwjllmdazjemq37wts6":["weeseandbeyond","Ryan Keefe"],
"wukbmpwzu2lxpqq524zllry6":["weebwitched","Summer Rain"],
"wyg7lkucdfiussjyoejjwmya":["weekendwook","weekend wook"],
"x3szizcibjt4qxisn6ysucr5":["weecabbage","Cabbage"],
"xgchbhpsgk62h46fninqrjj7":["weeguttersnipe","weeguttersnipe"],
"y6424yhlbt6aixcv6ryxtz2m":["weeb.casa","tinfoil"],
"yniq6vmkkonkmbes2zzccdrs":["weetimorous","Wee Timorous"],
"yr2jmq2xtsqepauf63do33oe":["weedavey","Sake man"],
"yuzpo37pf4n5mmixyktddmdh":["weedebee","Wouter de Boer"],
"yzxrdpjzocmh2h7amjo5jzkd":["weestables","West *Certified Real Werewolf*"],
"zsjuhoj7jmg6hgvziagqmzhk":"weewishes",
"dvw5ugq4qyfb2cnviqj4vfnq":["weep","weep"],
"tc222g3uqrydfjzlzztrqdbh":["weepjp","weepjp"],
"trtndhh5epox7s6tumhai5ry":"weed",
"azyo5me3gvqnoykgxo6loffb":["weevil","Foo Fighters"],
"milrbd7ez3gedh67wcmhw2u6":["weepingsnakes","MP"],
"vyvcygddmcgpgyolqm2nfiea":["weeks","Derek E. Weeks"],
"yvskx3m5p3zysgd4ttmiligb":"weekapaug401",
"y4d5rguswcpga4fhvwuagpki":["weepinbuddha","E.B. Cameron "],
"spewrv4rx7cr5xfgld6z6vjp":["weezythom","Thomer"],
"ecpry62z2yxyahrntlnrezbw":["weepingwillow","Willow"],
"q5jutpy4onwvwenbsxtfkybp":"weepingsponge",
"vs43u3ohd4gojtsuvjo77cpq":["weirdassweed","weird ass weed"],
"3meb6oshkqxyy4n2jhygbdzk":["weebilsurglace","Bird Bath Enthusiast "],
"iklarhskurv32v2lags5t2aa":["weekend","🦋"],
"hchww22hctx3o4kgszloijhh":"weezynthebrawd",
"kuifucvsbth5iy5zowc7yydc":"weekendconcierge",
"t6tzhkfamg5s5qgu5g4tkyw2":["weejus","Weejus"],
"hvim6ozvrvsxbmablih2gk4o":["weeliao","Weeliao"],
"mamqe2632epg7ktmrzmw6nx2":["weebservations","Jacob Chapman"],
"2czfv7dyfutvxtu6setp22lt":["weeette","치쥬"],
"5t65dkbase76rmkdmwt3ownb":["weedlordgoku","Weedlord Goku"],
"gmletgj2u3scqiwqsuc5qcaj":["weeeelson","The Holy Spearit"],
"bbrxqy3ctv7u4gteitl4bpzk":"weedcatholic",
"gdgwqemb7ra2xa4plrk6ases":["weefz","Weefz (Debbie 🐋)"],
"mtzx7l2febklvajzx44ddtoh":["weez","Luis Giles"],
"j5shptxwf2y55flj554sowcy":"weeevil",
"s47lgr5acy7sz47crq2gsn4w":["weegee","Kevin Smokler"],
"hixnfsjiu5hvw5hgpsnduppa":"weedwhacker",
"gw3qwyf5u6p7w2d6suvnh5sl":["weenald","Colonel Chugjug 📎"],
"7o7bpq63st7zrfzlpo7tg3ki":["weekbeforenext","April Sides"],
"pa6anzsjpf7pa5v4kg4b4xou":"weedithpiaf",
"aosnpihxmzep4asnckrbnnnn":["weee12","유운"],
"vyqweuwcdwupaixpmphgxhn4":["weeaboohotdog","Frank??"],
"6a7axhbet7chyj2jrwspnikp":["weedgenstein","Weedgenstein | ویدگنشتاین"],
"zyb3nf4w6cichufcktej35ns":["weesmdweeko","うい島田うい子"],
"7sajv3ygau7spnjvtpymycpr":["wee","عبدالعزيز"],
"c43l6lrl6mc2ljohrgr3sqh3":["weesesports","Lukas Weese"],
"corzfsab5pjrsurohkkkr2q4":["weegku","쨘님"],
"zjd67fpyjd4svaw3xnv4ykhm":["week","주"],
"2ly4pypdn53oaysniakpmjyx":"weekendwarrior",
"t5yvvphkwucruph6gbdganbm":["weeklything.com","Weekly Thing"],
"eyjabllr2yaoegagn3otmdes":"weelo",
"ko2f76t4syw2tkpi7p3l34el":"weebl",
"scfe5wid26pl3wgjotiohhun":["weezyl","weezyl"],
"xjttkbhelwah7lcastsoq4pi":["weedmubarak","Grim Knowledge"],
"5madwi7iv7xyd6hf2idmldbs":["weeum","Will B"],
"c4jra3ftdtjwjm622tm7rcry":["weeg","weego"],
"koaw6i5snkab7oetctrmmhjg":["weedbones","Roach"],
"7c6vu5ivtunq6g4icf3vdwjs":["weepeeman1","Weepeeman🔞 Comms open"],
"g3azlufjt4xpiu5qenx7rn6p":["weedkimchi","대마초김치"],
"re3kqgbdxcftgaexvo34xm2l":["weedmm22","모르핀쌀국수"],
"e6b7uzf3d2w6zaat6slhpft3":"weekdayxtacos",
"r666abxxlo6l4zfnoh7q3oih":["weewah","Weewah"],
"2f2qmptngzg233haj4qfen45":["weedcliff","James"],
"5hhzdgis33m7xjftpdhtkupr":["weedlord.gay","gender neutral draculx 🐬"],
"jj6hf6wldxzjdjgze7qlnjmx":"weelin",
"ce24ghsizihhno2s7wwla364":"weeyum",
"f5nqnx26yfrfnmuniwtzvsuj":["weekun","🔞  WeeKun  🔞  ART - COMMISSIONS OPEN! "],
"5m3yfefvubt3xdhuwwjnoi7d":["weedjesus","Weed Jesus "],
"bmclnmxn35mbr37q27pxuljd":["weekenddad420","Jirby"],
"ptlb4afxemhxgs2hpl5gan2i":["weesmeet","WEESMEET"],
"h776yyu5boptogai2xam55mi":["weevilbabe","erika, but here now "],
"ov5q66sjdl2fmoswqh3gj5vt":["weebjeet","JT 💜🤍🖤"],
"i4o366wtqgaruvjtjsu6fpco":["weebiejeebies","WeebieJeebies"],
"hcnqzsumb7hvnd5djp3hk75u":["ween","captain brian"],
"ipgan7ytob6i6yxlhddzoyu3":["weeker","World's saddest penis"],
"segqqjammhv2vrbvyncpuwxv":["weedgarf","glass bong for garf"],
"d7upl5swplksgbr2cf3y54yn":["weepingmoth","𝒔𝒐𝒎𝒂🍸"],
"vesv4w6mlkswmmuejalukc6b":["weell","will"],
"hsx7vh4au462fbgy5dx3s77p":["weebmerchant","Weeb Merchant"],
"e4aspakrtzrzlp4j26cit4rs":["weenus","Bobby Hicks"],
"fy5itf4fqnskv7bbga7q4p53":["weekenddracula","jd"],
"jkw4sdpwthgfxzcdcnfxzuer":["weedpupp","Aeon 🔞 6.99 OF"],
"5wnudfh44nkwdk3wfnbahk5n":["weedglob","Jarred Laos"],
"wuyb6hw2fo3azo5uraixo7bi":"weegie",
"xurujel3523j6gzlwkyj4rhh":["weesly","Weesly"],
"l7qfzqcttphkgaglmppes5m4":["weezerwoo","Weezer"],
"v6wdwouqp6iaclhgqvlsme6k":"weedprincess",
"6wpnxnesldlm3npupasn3ewo":["weeniedesu","madi"],
"o26mfjjk6skp7xzb7s3dhhml":"weeaboo",
"n2wj7s6cmef4qyzh64kpject":["weedkitty1435","ʚliver  ⏤͟͟͞͞  ★"],
"kqdyng55qhny4vifchzhlqkn":["weeburdoodles","Tequila Mockingbird"],
"nl5s6h7stqdlia6v4lnyrxwp":"weebber",
"ecf4dfngmfdrlzf3citipl7i":["weefuzzy","Owen Green"],
"6ids2zllsgk7ow7rkrj57ojk":["weepyking","WeepyKing"],
"ex3m3mijltj5s6wk47sahgh2":"weekesyjw",
"npp4typkako6pyrave2sr2po":["weeblespleen","Weeble Spleen"],
"da257dpfhlkdvo4hvgdmq3wu":"weeb",
"3au5fccutrl5ptmv6aehfseg":"weepkins",
"xwtjgf425osz4aps4vlo2ctq":["weezerfan100","james weezerfan"],
"c6eg5gmrbz4ax45zamhacqoq":"weebus",
"u2j3hgn4ocm7nbcexnmrwfer":["weesnaw","Remi"],
"r26olnfoai6stfwp3k3mtr66":["weekendroses","Milana R"],
"ntlc2vtpw25sresrnmhw3roj":["weedfingers","What the fuck"],
"b44cha5po2iipmicgcs2td3q":"weedle-beedle",
"yvc4ojjgdzgr7txdhoch5jz5":["weebindenial","Shizi"],
"32wztsqker2wh27ot2eub67t":["weevilwolf","Gem Robinson-Wilson"],
"irm54vgj7uho3x4t5luk66ai":["weem","weem"],
"oopjfss4qvmqkg344r7fhm3t":["weeze","Weeze"],
"veyimiwy6ce2lstvko762dt7":["weebspostingls","Weebs Posting Their L's Online"],
"44ta3mcm4xew2xfw45zclffo":["weekendboy","Libby🐰"],
"sfs4qnq4esot3hclezhi7uma":["weerdgrrl","weerdgrrl "],
"fyrj5ls5vuej3kdbrxzkuyvr":["weepiiee","weepiiee ☆"],
"m5czawhkyzsa7t6usnil5zbz":"weegii",
"htlhubfrl6qquy46racaxtua":"weedenjoyer",
"35n3echgxe723lddxhka7pmf":["weer","Weer"],
"4funa5in6ty2fomx3th6f6v4":["weeemo","Brian"],
"wcwnbk2cteetrfdkjvcxlsat":"weekender",
"f2wyqj4dri6j2oeo4266zsvr":["weeboo","Hazel :3"],
"gzkd2ep4bh7niwpi7ojpyz3b":["weewidget","WeeWidget (Comms Open)"],
"3rl23j2pslusflc7ehpw4wop":"weedachu69",
"whn3mvntusjl3cmv36m2ldky":"weekendsky",
"hvjdy5gb34ywdsyqemwwolj6":["weekendpies","Parker"],
"ujfofhzvr2o5i7ixt4y6mzai":["weeeaananne","анія"],
"4q6ysfstxzj5b7vprj4jt7ga":"weedwick",
"rgzf45qpakkukiug7afi56zc":"weedeb",
"ptq2h22p4shpkq6t6vnjz5pi":["weedeater","cream"],
"jfopnyqhfpm5rsfw32n42anr":"weebking125",
"neiy6sgyxvuyiosj6yh3y4qm":["weesio","Wee_Sio"],
"pnnx7uq32q7ycvsl32nft7hw":["weeppiko","Elias Josué"],
"4zzl2vlw76wqu2yylmccnmq7":"weeaboowilliam",
"qcou23x7sp5vmxa2d2vnk4pb":["weeksy","Weeksy"],
"7bszax3wu7oxyjymd7ill5o2":["weedsorcerer","big chief "],
"snqd6oxw4jdd363na2deh5du":"weembles",
"5owan7bu4wnxain4lym5b3jo":["weekapaug","Kevin"],
"ztg3j6ay7r4nf6lpdxaliz7x":["weeniewaifu","anna"],
"3mcdaophpecjvoikepceqbze":"weegol",
"touaei3qp5gbprdcgzrpc5x3":["weello","Weello"],
"vwze4lc4xdgr3txeedew3jbt":"weenofficial",
"vbngra34scmop7vwclkt322j":"weepsheep8",
"fqsh4xu4sjxrazwqmxekeqfd":["weebyr.com","Weebyr"],
"wmvl3oxzpf5ahle5hjrpnw2e":["weeryan17","weeryan17"],
"uxbizzbg272kdtrdepej7727":["weewizzylizzy","WeeWizzyLizzy"],
"rwqg44mwmqu3lqzwc4k67n6j":["weewim","Weewim"],
"v4hzay6swfkcgkzngw4ekm6l":"weegee26",
"3p7ginl6mdwdhvhkjshqm5ea":"weefbellington",
"oy4rt3vwtnfz6xgi6oevbbvb":"weemby",
"wduwlqip7zbslr5xgrrc5xeq":["weezey","Weezey"],
"eirqxfjvkkysqztghfgpeb54":["weeawolfad","𖤐 WeeawolfAD 𖤐"],
"3xowwbabvdwgkoqdzwb5ulqj":["weeetalert","смішний шмурдяк"],
"lkgkrqkcpylpusxsdkxw4rzb":"weegee24",
"vuaquth6buwdcximp46lgktq":["weebirdie","weebirdie"],
"3nmcwa4xwul2er6dezevg77t":"weedyabyss",
"vq2ggvryk775awjnjl25shrg":["weeformer","Weeformer"],
"iq42x6y7tokq72qph5ntmfar":["weeabooshu","weeaboo Shu"],
"mhqkq7zenuke5x5fjtguthvp":"weebabix",
"jcv5mjyzlwrhjdqoviioyvmy":"weeplord",
"3toahckadnnye6jfafmu3rhc":["weekoldcoke","Kevin Watts"],
"64b5ow6rnydutjcpmrpaop5n":"weewooart",
"z64xxuwqiucqlrkxjbq3cnh4":"weebsauce",
"5wofjenz2s5vys2vg336tpxa":"weedwick0",
"mkfmxs5vxwdsjvmxc67am5gu":["weegiejoe","JCB"],
"pkhtjkbd52qdg2xd2ujfpl6z":["weekendhiatus","The Purple Horse 🔜 UKPC"],
"3eg6ntvzk5ei4gumrkvhswfr":["weeb.remindergg.xyz","weebwashere"],
"5nvqnko564lvnpbc5zizjtkm":["weezerpedia","Weezerpedia"],
"iet3rc3bhygdxdqcpwg66h3e":["weebsrsuperior","WeebsRSuperior"],
"ycq5czbdnrxw5pird4nryx72":["weedsorcereress","Maryyyyyyyyy"],
"kts4gyjwz2jq2p45kj3rdej3":["weebtrash04","It's me, Weeb 👋"],
"x7a7so6h5cps3bzavbpkqweu":"weekend-nachos",
"t3ebjuhrpyj5frxmp3jmal25":"weeds",
"j45qmhp4x4wne7o6vb3ggdcp":["weejax","Wee Jax"],
"zojfrsq4d55n62oo772kp2io":["weemansgin","Andy Martin "],
"f74u52q2v5tkvsqsg44ikrck":"wees",
"yr5mlevizpskxfedf53z3ko2":["weeto","UwU Weeto 🔧💙 Vtuber"],
"c72kbehubcagu66m3gel37np":"weedollydoom",
"3yrahr4dl5mzk6vyh5gggdiu":["weennygson","Weny"],
"5vkrsj3r57inya7fheeejhy2":"weerasak",
"32xzbd45oavmu43nj43gqq3r":"weekly",
"r2asub2g622n7jama7hk3nbi":["weeknd","Abel Tesfaye"],
"ncg4ewwnuumtklygvxkaolfg":"weedinthekailyard",
"buum5bfu6x6d7xbi2qing4fp":["weedisvegan","Ness "],
"znbykmjt24qnmcbrtgrzfswf":["weegee2","Weegee"],
"jvr7doq2lyblpjftkq27v6k7":["weese","Husky Weeskers"],
"3pgwy3wqyq3gvt3sneazawij":["weegiee","Weegie"],
"vii3mjry56finulchbdkuxwb":["weebee","Wilson Jr"],
"7gubt3jmi3ll7w5du3z4kmrv":["weebot","Weebot The Robot"],
"kadzbrnyfypbokhgihuvvl2v":["weezus","Lou-Weezus"],
"gr25lcp4zpx2zaipxvazdfjj":["weedeagle","Alan Holt"],
"zeysnlfohxmy6pu3esheoil2":["weenerwoman","Andrea Werhun"],
"t53dgqcmvthqjxxislddjsg2":["weebleny","weebleny"],
"szmbqn3ayvos4zexojcrdx7g":["weedthewolf","Weed"],
"l4zchylnpnn7apu7eqv2bj3s":["weeaboogamerxad","Pik the Spinda!"],
"6ssrhlvyczdkbok6o6o4oyie":"weeners",
"b67weyi63au45fnldmps5q3e":["weeeee","Eduardo"],
"w7uv6w4wf6hwld4xbbfljwb7":["weevic","Vicky"],
"prvff6x66l4qzjkxezgdfn3f":"weeirishpete",
"dp732bi7spiyusdtfzxvguo2":["weepycupid","des"],
"5hjrcje3htrdn7hjnjzyzgfw":["weegeepie.com","Weegeepie"],
"7gqarmdcux3gbffosbju5yun":["weedleplop","Weedleplop"],
"gcoozbcjooumzodgoxuh4iqw":"weemarie",
"mowiyzuhak3bsdss7memnhfr":["weedmemlo","lame"],
"as3xw6bwl2xcl5bl5hx6lkvy":["weavingweevil","Weaving Weevil Crochet 🧶"],
"aho62nf6wm4i6lyvbnpf2njd":["weerawatk","Weerawat Kunsee"],
"5rnyvxdfgmazggg73qcnrqxj":"weendogz",
"x4xn2zqiv4p7abbzo2pzxaf6":["weerabbit95","WEERABBIT95"],
"wreuto7dvqj3axzslkxkonsc":["weerthof","🟡 Michiel van de Weerthof"],
"uwsavtcqtxbfya5xksvczsga":"weecent",
"pykxvqfjlypamwd7zmzb6v47":["weeslate","Slate, but smol"],
"ui7rd7iwlnlycb33eyer3aea":["weebpaisen","WIEN BRAINROT"],
"ub2estcijtpjqsyx7kccm56b":["weedgato","Weed Cat"],
"rwmzurfayokalem5cmz5xyk5":["weedlegrass","Weedlegrass"],
"vtbg5nbx2ylrgjn7wyux5wbl":["weegreen","WeeGreen☘️"],
"ran4qo57h3hw3nakr234o4ky":["weeeeeeeeeed","wendy"],
"muwsx3qv5lh27mcbbnc66xgl":"weedgod69",
"55krbqe5jplb4quejzazzwtn":["weepinbell","weepinbell"],
"avnog7x5w3i6mc7yq2i34vjz":["weezing","weezing"],
"eumc5bvalug56mgqzdwbji2c":["weepingmarengo","Reba"],
"43n3w7ogdxcwzpuhfvlq5ayv":"weebwithakeeb",
"mrarz6ccmzhvxs3hh4bm2snk":["weecology","weecology"],
"e5bhpyypb62voyebnyeejhcm":["weebeastie","Wee Beastie"],
"juh2byq2o2gpjqbnvy7ahhq6":"weedbrownie",
"cj5jee4mwxtg567ntacbwask":"weebking127",
"6v46h5m6iefddud2hojew7kb":"weekendwhorier",
"wnncsttswsvm6cqsey5phxt4":["weetso","Weetso"],
"4myrsvmb3fv35k3au5njzda7":["weeniehutjr","sam 😮‍💨"],
"zvo257tq46h5itcso6fswmnv":["weepiglet","Piglet"],
"e275lweo4nhr7cf45y6kg4wp":"weedboner",
"cbo2r2h7f3hchl3trxvng6wm":"weeos",
"q623subqjmi2dovafhbi5ylh":["weebkissen","Oktoplush"],
"zunq4mxsai7vbjcej3qnrnnc":["weenus-tf","Claire Weenus 🔞"],
"wsvbetcdlbjyykkq2fcr5a7y":["weemaddz","Maddie 🏴󠁧󠁢󠁳󠁣󠁴󠁿"],
"vfmjzuitngbcnirklu3tvcb7":["weecuppatea","WeeCuppaTea"],
"rea3dqqfaz6bdswijoqsk7jp":"weepsheep21",
"oawslgnbd4qfmzfbx23xt2pl":"weeb23",
"t7flglxy5d32k4huiha26qdx":["weencuisine","Ween Cuisine"],
"fuxv4yd3canwmes6oah7ik7x":"weeeeeeeeee",
"eiijlf2t4jawaxkdtji2zjp2":"weebking1223",
"umzd7qwn6o2u6arubrd26gk2":["weekheal","Weekheal"],
"wxm4mqx55upz5xbkz7zxvg6x":["weeberson","Weeb"],
"o5ptinqqypl4mbulgc2pdcks":["weeamood","superweeamoon (full power)"],
"cy26w27p6eo6kuc2nwj5ygd7":["week99er","Becky Fixel"],
"f4smzf5gow7f5ih6ysdxi2pb":["weeniebagel","dak bagel"],
"oourwaoayclkb64axlc4yexl":"weebs",
"yqqqgtymldmuagp3uy6uqyji":["weerteex","WeerTeex"],
"m3qbihc7clnnzvsapdadvm2r":["weejay","Wee-Jay"],
"nhqllroqki64dwzhq574z42x":["weekendpanties","beetlejess"],
"33vvqhicultlbqlqwne6flaf":"weejaney",
"nt3d7kdvufwolox4f6vcej6a":["weenwoon","Crim"],
"qn27ztsqycuya2kncqxdqjir":["weepiestwillow","weepiestwillow 🐀"],
"ml3uhdkwl7gfnb6iu6dbswyd":"weezle",
"vdd6fw2dsfzclr7i4xjkq7ct":["weeb-heaven.de","Nici"],
"7b5fpympgh5bek6e3zq45u52":["weefywoo","weef"],
"jeklcbna6263utsbm4qqmgbi":"weepytimetea",
"lgg2jdmshbstvlkj2wj56wnv":["weemissdee","Deborah McCormick"],
"eq6elf3b2sivlwznfdwig4lg":"weekapaug009",
"vhegic32dxghrslheh4rk7m3":["weezl","Weezl"],
"baxiti5mw7ckw27urcrru37y":"weebsty",
"brcdbnsojc4v6p3azrjjbwjx":"weebairns",
"nu4osw7iuvvxt6m7cwtumr6r":"weepingwillows",
"abjegke5ekl2iop6rc2tjvu2":["weeabuuuu","weebu🤖VTUBER"],
"pmf4xcbjnhea43nrqhqtphef":["weedgoku","WEED GOKU"],
"4475dyc5lgbmm4l7rwzustxs":["weedpiss","jd"],
"lnmdgwdm5i3c563dg2ae6jun":"weekscommadanny",
"tgl6lda7nqz7ynuilzyqiqoh":["weebtrashlife","Rebecca Chambers Enjoyer"],
"v4ac3ckpyr752bmeezbcistr":["weedwinked","Anna"],
"z5eojnwu37b3af5dkxtkvptp":["weebologist","Weebologist"],
"5zcil4zxmioiovt346be7476":["weedbaby","weedbaby"],
"byijeorgd4rcmefkv7nmz4ij":["weeddog","Weed Dog ΘΔ🍂 🔞🔞"],
"3wqrawq2fstyophrixv5xs2x":["weeddragon.gay","Derg"],
"eydz2xvyfkfommopijs2kim2":["weetlebeetle","Nebula"],
"swzvxawkygdftzgc76poxuq2":"weedaunt",
"k4zyyqgjz4oqy4pincdxoqce":"weepingpenitent",
"qvwufnkgwj3zluxqqxutqpwt":"weesparrow",
"wtgipm4zccsohzndawbjfrxn":["weebi","Weebi One"],
"v7gjpvn22zdzzos2p2lzq4tq":["weethreequarter","Ree"],
"cxnizxgaoflpq5pvz2svmjcl":["weeping-willow","blue "],
"fgb4sq3mfnzwukcjjyfyezyj":["weaboomeister","Weeb"],
"p7fw3ptmbxya3xyrglwbnlpv":["weeladdie","Wee Laddie 🎨🖌"],
"ervwpkvlyeplqrsvifntw765":["weebsquatch","WeebSquatch"],
"hjbgwepnwxfrcbm5vvqtnd7t":["weedlover69","sam swisher"],
"cybswkbfc5hrozzynbvughqe":["weeddemon","Weed Demon | Vtuber/Metal Musician"],
"g54mw3a53no5ttisl7zum6kn":["weegee117","WeeGee"],
"swty62zjplg6cmavj2wkbrgw":["weebra","Weebra (gone fishing)🏳️‍⚧️"],
"6ckg4wnbogpdi2kxb6qxxh2a":["weeping-j","weeping-j"],
"kqelsbklncky2jps5yabzp25":["weebtrashgoblin","weebtrash"],
"m7ayu5e5qgsyidozljxywakh":["weedjs","Dave"],
"4xely56ob3lqyqsw6bcenraf":["weekeew","일주일"],
"4z7kjyjyim4p5kouoqwac7br":"weelyfactoids",
"swma2nnzasyihwbkx2v6zmue":["weeklywitcher","WeeklyWitcherPrompts"],
"jtu42nir52bzaievm7qitcx3":["weelittlenori","Nori"],
"2qoofajxhfwensn7g43oeedz":["weemie","The All Weeming Eye"],
"zu7bkztsualh622ctgh4slm5":["weejohnfk","John"],
"xq2zmk2giln3uizupmltqwii":["weepingangel","Alba ✨☠️"],
"2ruvvk2a4o7jyyqqveshzr7p":["weef","weef \"m\" slider"],
"sdqpjsakdewx7ho5wywgix3h":"weenerman",
"zlqf252jajkkylm3volju7gl":["weefairyfabi","Fabi"],
"urhc4wx6gefdn7lauit23eo2":["weewoo","Ulf"],
"zqjxwfva3wrxqni73mnbrjxp":["weenievevo","Hughie Lugnuts"],
"hk4prgulxuckb76yoau4kczv":["weebykat","Kat the struggler"],
"iwtow5gbdmxfjoyeyxet36v3":["weebsteve","Weebsteve"],
"77dimroap4urzyaqrrwnmhkn":["weeedzmane420","the tummy tickler :)"],
"cvd5blnbkn5rsbrati56mhlr":["weezomaster","WeezoMaster"],
"shd6vdqzwto7v4huwfqqbphl":"weegion",
"u2i6c5vbqtul4kw5lj6g4luu":"wee-donna",
"l23n7kfumr2lip24lpuqpmpl":["weemy96","Rouwei Wolf"],
"vwpwx3hirggd45dkz22lx2bs":"weezerc",
"4h35afwsemn7vzu2yqucmkqy":["weegee133","weegee "],
"uz3g7tubrznj5tcxk5tigin5":["weepywheely","WeepyWheely ~Comms Open~"],
"hbyilpk5owv26y6qqxiucfs4":"weedplaid",
"wsh36su7qzudvr5duwmbckny":"weedwick21",
"tokpqyctttaz6hwe6lyzwnu5":["weeklyspectator","Glenn Check "],
"bxsxdyctokeva3zscrupep4q":["weertc","weert canzler"],
"loku2wi6naor3anibnk7f7bl":["weepingwillow88","di_zande"],
"bwwjljcho7niuwpwxdq3kwlk":["weeblis","Weeblis"],
"iv5muizrtfga5tkhuttz5kly":["weebossdog","Christopher"],
"4aum7u6jzijcu52kssjqehxm":"weesel",
"3fd5xdrivrjfhwmad36zn2f3":["weebhunter","Ricky"],
"u3fxojbq6bfbskdlfyb2hn4j":["weed03","IM"],
"ziwcvmr7rpmn7ofwrdnlc5o5":["weecoo","mimi"],
"ij3nfzayy2huwdiilfxkjq5h":["weenieweediweeki","Dash Camgirl"],
"ushc65rprt5zejdgwqjrmcun":["ween33","Sebastian"],
"gl23ybliabtdq5prfmybxqmm":"weeboss",
"ksqnzc6gobl4sybmtk7socq6":["weenut1919","Chloe"],
"gg4pqdiana6v55aigumt2g26":["weeego","weeego"],
"myp45l7c3spjtfgijc7lotjd":["weenuk","weenuk"],
"mme7l2qot44yeklvlwqwrmyj":["weepingwillow97","Bird"],
"3qfkzpzendmxjoyfi7tsi44n":["weeanna","AnnaWee"],
"cooat6rl7yf5ljjp6zweqq3c":["weetabixsu","bixsu"],
"pm6d4tymieoihqn6fiodeuvt":["weebshii","Weebshii"],
"leeliisuowhm2sek6py5pwcw":["weesejen","Jennifer Weese"],
"gbgug7vezfkwhf425zn3pwqv":"weebusracoonus",
"ck72shpxb364wfuqift2vtt7":["weemina","weemina"],
"l5gkzaaoyjn6y6ifbfulbb5a":["weenee","weenee"],
"wcx7hrrxxfsf343ufljdbhep":"weezer66",
"qa3akmvdkdv5stdmzjxfvsmr":["weeziz","Lou"],
"oibganhv63qoryame5zlxqnq":"weezylations",
"hguyaecel4x3qhvjcfgkirc3":["weebdev","Weeby Dev"],
"ahjjul7kqefaq6imiqmljnnt":["weekendbastard","primm_slim ⚙️"],
"u4a2txpjrmt2lagk7lrp2ki5":["weezel","Weezel"],
"j46a4x2v3pb723jp6tzopalm":["weeeeeee","muskrat appreciator"],
"vriy6qhnpmnqvbk6apf2pzel":["weefreeme","Weefreeme"],
"hedu3576ulhnag3lw4j2hxtt":["weeghostie","Niko"],
"fxi7rxygzisnk4ylnphxfnbw":["weejburbles","wigi🤍"],
"vulrqjq5uvsgssolmrksb37u":["weedlesbian","moss"],
"jxhygjdpbqnomzusqvfeu6ft":"weebongnugz007",
"zqcbu2mriteqtitaouotwx3n":["weebeastie162","Beastie"],
"sox7zj5cyccpkyxaidwgsmhs":["weeznbeez","Mitchallen Man"],
"rake4uwyg7bpx6jby3dvwtuu":["weeblur","weeblur"],
"zcsiuhq2n5mkvz7tp34qgjbf":["weegeepai","Ci da moff"],
"c5l5mxgosf66hrhbfxxfrdsp":"weegyboard",
"unjd6dlf6wfqtyslerifwbvj":"weedalee",
"dz3gtbfn43ohfk7egiqdjplv":["weekswriter","Sean Weeks"],
"ay3q3hf6s4oc5ycrct2w4rok":["weedgoku69","no"],
"7lxuieejdq5cpdcqircaelvn":"weebking1219",
"j76nz2lt54j5c2ihn4sm6ltu":"weepsheep19",
"kdaiwxcatrbkbqgs6hgwjabp":"weegee215",
"b727olffwwim37ur2zunk3zz":["wedsr","Weedy"],
"twydd45cs6phwdrbhf7hnueh":"weezie",
"p4m4bjjbin27zn7abwlk5lhq":["weedaibhidh","Dàibhidh "],
"7h2ucqxsqr3c55mj6cs5i3wz":["weech","weech"],
"zj25m7phauwyajib7im2mu5e":["weetybred","Weetybred"],
"rdfsmt4u6u2czd5hzkukucig":["weegeesqueegee","Weegee"],
"fk6r6yfngvvvfhce2jw4iekl":["weeknd.dev","Synz"],
"gi26j5jldo5oe6gbjqgk6x2c":["weezor","Wee"],
"kw6ueapucotjdbtyoeziy3nw":["weebbot","The Weeb Bot 🔞"],
"t2qj7ftk42skafmekpumnyxq":["weeaboowilkins","Wilkins"],
"pxfz2c3fexcbt3m6dcyvyl5i":["westhefitting","WeeTheFitting"],
"dg3u4xucsykhjdr5jndkke3j":["weederstand","Weederstand "],
"nhhh2bxdin7r2rtgnzbrmimh":"weedbutt",
"3gmwapgsmbta5nnoddugznto":["weedergaenger","Weedergänger"],
"fzbfp2arsfnf37ra4p2o4vqc":"weendel",
"nilddwkpwkz2xlvbqj7v3ugi":["weet","weet"],
"oc3y7vuojj7q7wonzc45bs3o":["weeeeevil","WeevilSarah"],
"dsv33xbpfzsnf7mcs64yna5o":["weedyosuke","Stoner Yosuke"],
"vd6gyfhpfty46wykjs5qa26l":["weekandy","WeekAndy"],
"hay4fopwgsbtovcq45f7hyf2":["weetanuki","たぬ Tanu"],
"k7ktdvj5cbfwqtf5kf4mvaer":"weedwolf",
"wjqm54jypgyzuz47llgrisok":["weebusmcdweebus","Weebus McDweebus"],
"hk6zltl333fmtjy5k33lpirf":["weemelah11","Joe"],
"37sqczse7n25cqopi7bwehxs":["weezerlyricbot","Weezer Lyric Bot"],
"vcj42t3mtavk3qllg5r722eq":["weesho","Biso Parajuli"],
"q64lg4ohdxx7gh43bi7snu5c":["weegee25","SSS | WeeGee "],
"qjheoszg6cyrxvr64e2igs25":"weedfur5",
"6xnfy64gnuzoe7oosah26vxl":"weeb4",
"opw3324dyyz6ydu3jg6ptmnf":"weegee219",
"oxnu2nj2awbhe3gbeeiigopo":["weenwem","Weenwem"],
"wpwvxgba7uvfl64ouvxy3rhs":["weeno","weeno"],
"kes55g5f5twai24lawzebeq3":["weebbys","Weebbys"],
"sroviawnmtmkvmvwaw5kfbh2":"weegie-bored",
"ucvwnacdlc2ypqxr6ld25wh3":["weewarr","WeekWarrporub"],
"725twxiwjqvxdkofcjcxhwkm":["weevmo","Leo"],
"gjv3o7pljx377hnyn76cqz4y":["weedy","Weedy"],
"qcbeond4msmxp6pixgs3mcft":"weetrick",
"myd2febqlxtriy2nmtyr3qjw":"weebsauced",
"fs6flsalzlmlrbr7tiuvp5em":["weevll","newt 🐛"],
"ofkifx3cozw5kshnogdeoo4m":"weedkusher",
"zunxtrdhmqt2ddtbxcfrisaf":"weeweebinky",
"epjvd3fqxzkkcrt7e26qvhpp":["weebmaster","Orandon"],
"kqkvuj7vi5gnvw634khvfw6h":["wee-nell","Wee Nell"],
"z7ygedxr4aswrm56kjtq6lqc":["weeni","Weeni Random"],
"w25nre5wvdxgxdr5j2ljwwa5":["weepixxxie","Pixxxie LaRue - NO PPV! "],
"miarkdhu4oy3g5ilws2wm52l":["weeniewonsh","WeenieWonsh"],
"7qrevaaptmrz7vspxvjqrkdp":["weeviljester","clug (clown bug)"],
"ldchi3qftb4w5yo55a5dntbm":["weeville","Tea Gremlin"],
"zewgihv6qughm4h3l7bt36v7":["weeaboospacecommie","WeeabooSpaceCommunist"],
"jco4xe5xsdvqoclmawbx7hfx":["weekends","weekend"],
"sm652nw3nbtznfnawm6x2zt6":["weebwizerd","WeebWizerd"],
"smjnzb3y66r5mtcunh5xcq42":["weektimezest","WeektimeZest"],
"osluxefvvc4lec7ik3rq6h3g":"weebydustox",
"fikzis42adijvgxkyakpwm3x":["weeping-scorpio","Oz 🇵🇸"],
"gxe4hb4tawoyfxxdeygssufr":"weeros",
"fmds2pbauw3o64p5t6ovdt4n":["weenhallo","Alex Supertramp"],
"dkwrmsfzbj6sdu5l4cly27ge":["weebalu","Lu"],
"s347o2duzypswvax42wol5uk":["weezkii","weez 🍊"],
"evgqtpq5kd75vo2mxrvzya5o":"weeniebutt",
"rfm5cano4abfi33lvxd6ris7":["weezythebat","Weezy"],
"l5h44x4lf2lxiqpzdjxbh427":["weebboi105","Weeb boi"],
"hzo44tsh4uc4mfux6b7icwk4":["weedseller98","weedseller98"],
"5yjkn4a4sqd6zo6yazaflexq":["weezee","Zoë"],
"5cfiax2jp6q7voqlkitby4tn":["weewoahwoo","Woo"],
"5ap32ox7n75tvgepicqqekfp":["weedybo","WeedyBo"],
"y44gf4mm7lshs4zz5ffjhxgh":["weezette","Weezette "],
"laj2l2khzqhtrhwcktxfbsi5":"weenietot",
"oc54ijf6ir7tzvuunjcjttr3":"weedsil",
"fugmqi6v3hihhx25mmlw6wix":["weedsmokingguy","BongWaterSommelier"],
"cefd4f6zasbtex2dycbiy55u":["weekendateffys","Weekend at Effy’s "],
"3aiavls2hup5cqb46erk3hty":"weezw",
"lz2277w7tskd7egez7gkkees":["weezo","Weezo"],
"p4bkevedkvnd7g64zc4vjsm2":["weeklyosm","weeklyOSM"],
"dafjm5vqa7s2cxhv2epicavf":"weedmango420",
"jvbky2x7vcpfol7yfvv45k6r":"weebqueenbaepsae",
"ygbcet7o53uovegok6gdaygh":["weeedesu","raemz"],
"yrwca6o6o4ti7el4k467l3hf":["weebsaster","Weebsaster"],
"2efn5iezfxlujtjhyqf63teq":["weeklygeek","Weekly Geek"],
"5744weqegzosdeykol7n5zdx":["weetz","weetz"],
"qz7ht326gvmeysjhv3rue2tz":["weezerjap","weewe"],
"giyxquy6fsi7ghq2f2fmgppe":"weewoowombat",
"wobvfgp5sawqqeyeynt34zwp":["weeenaku","weeenaku"],
"4gxqozbpocsrh5fudzl5kzfg":"weewulliewinky",
"ojzzmoflzvb2ghnmgrdempuh":["weejapeeja","🎃 WeejaPeeja! 🎃"],
"j4bkv5qkhmzm6uq3mxjb2fai":"weebbaa",
"wjcy2rbtqr3jnyiipee4nkzk":"weejiboard",
"lgl47254qzdu7pi6ctdjbuth":["weegeedutchie","WG"],
"f6me7hl3az2y2njzwgc774ml":["weepingshrooms","Weeping Shroomies "],
"rcqltzlvkmyurccz22ssx7ys":"weezerstillgood",
"7dm26a4j6keq5jxtvq5qmik3":["weebism","Chara 🐇"],
"e56xmuif3u3xprehrcgg5kai":["weepyangel","wren"],
"v4rpxz5rjssaijx4thppvoqz":["weebchi","Chi"],
"erjpwdgjprypb2vjox53cxn2":["weekdayp","김계춘"],
"ctxyefbrwbeflyfjrjajzzcv":"weedlewood",
"spst2jo6nwlutvt354ozwief":["weefergie","Wee Fergie"],
"o74mi5yodmfhfv57byaxk7ns":["weeeeeeeeeee","LilithIsLifeLilithIsLove"],
"q52zvge35qcczstl5rmiwcrb":["weedladyc","@LadyFindomHb "],
"qielmo6y4bcfsgmr2ipehn34":["weedendorffer","Élo"],
"avxppjuf4xyppt57yophxalw":["weewoodle","WeeWoodle"],
"5b4dhl26honod775sg4ceq54":["weepingliberty","Libby"],
"qqjtb3ix2zmm3wj4uyp7prfl":"wee-rogue",
"evshjacporb7hihajeaxesne":["weepywillow","Willow"],
"dslqwinlnazpvufrhvcyikf3":["weedgaru3902","김가루"],
"6652h7twdz4mqzaybrnilz2g":["weegranny","Wee granny Lyn "],
"ci2bwlrho7opqkrqo2ewelea":["weeby","「W E E B Y」"],
"2awjvym6mhikmzhkg6xtcu6j":["weekendclock","Clock"],
"hqzba7tn5pqq3zhcmre3qqg6":"weeny",
"xfvmkcaxn3ckhfxni73sjxfn":["weirdlyweekly","WeirdlyWeekly"],
"3mx7xm6lzoif2aivn27kidi6":["weedhopper","Nathalie"],
"vxroj5bu5e4yurdqslgq7xm2":["weepingcat","Weeping Cat"],
"iaycjmyxbcm6zvr6rie64wu2":"wee-echie",
"fmkzi4zqulns5nay2qx727qk":"weekstrong",
"t6byr6rfq33bmb2lhnlzbjvb":["weepingwister1a","WeepingWister1a"],
"g5unohkg4chz2yibr4aolie7":["weebneet","WeebNeet"],
"u4eeiakud2azjpfkexiu2wrc":["whataweek","What a week, huh"],
"d5xmtetjmfsm7rjxwttlh4hy":["whataweekhuh","What a week, huh? all Wednesdays"],
"zxsogixavzjflt77opobszt2":["whataweeklemon","What a Week, Huh?"],
"mqhmuijg6v32qcyfadnfmgof":["wiggleweezel","Wiggle Weezel"],
"kgkibb72gr3fivuff3widzj4":["willowreal","WEEPING WILLOW 🏳️‍⚧️"],
"3t2okwdqs4mo34kg2cax7336":["wkcooldown","The Weekly Cooldown Podcast"],
"o6tfjn2tlcbtntzqx5xlznni":["wkndwalker","Weekend Walker"],
"2grtsr26uzctsp5evwxyp6id":["wondermixtape","Shannon McWeeney"],
"cubp7ju5bjuvdrug3qiaxunk":["wolfmanzack","Weed Detective "],
"d7dvy7e3sihah5mmrcmbmrk5":["worldwideweeb","Worldwide Weeb"],
"azpyspbn3b3khkt6ynqmtqgz":["wpposters","Weekly Planet Posters"],
"syftgxeqo6hbgi34cyigzkq3":["wpafw","Western PA Furry Weekend"],
"kk23dbj4ijywmvfhpirqjoqj":["wsstalkback","Weekly Shougakukan Edition"],
"zcaqnbu3jfxosekbtydq6t3q":["wwaw","Weeb With A Wacom"],
"ga3q7pd5lt46emt5avczmxva":["wynndygoon","Wynndygoon Weeps"],
"wwyprhvfkgj54eykcgswljrh":["xdeewolfx","weewolf"],
"xui6ynyc6xugbq7zvd5bclyx":["xteweeb","xte Weeb"],
"4nb5ighj5i5lfqsjj4iemgas":["yea","micheal phelps (weed)"],
"jh5ncbk4u5rlgfqj3rtr3qqt":["yeenpeenqueen","Yeen stink weed"],
"6fedi35fj52pak3p2vyueufw":["yellmi","weenie"],
"mjytdwtr2rkvzqeemdg3nors":["zacharyweeks","Zachary Weeks | Disability Advocate ♿️"],
"4ugwclljgrycfmz3dzdfitvk":["zaweeg","ZaWeeg"]
}
