{
"y2bcrwm5a3jnzmt32chldf23":["alfredwegener","Alfred Lothar Wegener"],
"ptrorttr33fstpzzoq6gxlzl":["aufdemweg","aufdemWeg "],
"co636ksobjpoxdnv3t4hi5mj":["carmenwegge","Carmen Wegge"],
"5pw3ndjvqwngf5etlrsqdrdt":["christophploss","Christoph Ploss : hier wegen gendern"],
"x6pgbejszocc4cjg6wgqnovj":["cnothelle","Auf dem Weg "],
"inkrqnb4erctyndhlzctsqdt":["copacetic.page","Max Weger"],
"i4zsmtuf7ubaicmysw3zja52":["coolhistorian","Austin Wegener"],
"6duwhg63pco37elmanw37cyr":["cwegscheider","Carsten Wegscheider"],
"7yklcn2rry2dhwbzqyxwz6bk":["danielderspaniel","Der Wegstein📯"],
"rxavjldofhrrn46jiepfnpia":["danielvonwegen","Daniel von Wegen"],
"wsflaqwjtcv2b2ueforo246p":["danielweggeland","Daniel Weggeland"],
"ltoqrwte4j2d4rva6fqvkfvk":["derdennis","Dennis Wegner"],
"2fs53sdxygnqg2dys5zebuno":["denisweger","Denis Weger"],
"n6pcjuprs3bbyhdmgy3ldgmg":["denniswegner","Dennis Wegner"],
"r5yi3kuhoxmqvjzjtobe7vqb":["derwegrenner","DerWegrenner"],
"wq4vfkhuhcbas67743rvq7nd":["dietnoods","Jody Wegner - Looking for STORYBOARD work!!!"],
"oq6qaemjpeip6xry3tyou2sg":["draufhalten","Tim Wegener"],
"evnkvmdisukzc3zoonkgm2of":["evawegner","Eva Wegner"],
"z2askceyddr57lcjzsudkjsl":["gesinewegner","Gesine Wegner"],
"fqzv423zsyyqqkdbusbxf57w":["goweganmitwe","Wegan mit W (she/her)"],
"aay4afglz44g6h4hmm4gcipb":["halblogisch.de","Komm da weg, fass' das nicht an!"],
"mzhyt4jghqqj7lakbbpbvaoc":["herstory2","Monica Wegner"],
"5ld764klhf7gb5wljqlymq4n":["heikewegener","Heike Wegener"],
"v5itc5kpu55ezaferbq57e7w":["imoweg","Imogen Wegman"],
"slaombe4knum5sliqily7qm7":["innerer-frieden","Der Weg zum inneren Frieden"],
"3kluyezx3f3zkf4illve3ov6":["istdaskunst","Das kann weg"],
"blvk4j4rupcid46pugi7xa3c":["jakobwegmann","Jakob Wegmann"],
"hnythumhrabxdl4nzvz5idgy":["jakobpgflr","Jakob Wegener"],
"bi7i7xefya5rfftu7bn4eydx":["jillwegrzyn","Jill Wegrzyn"],
"h2qarnfeutur7xogxab53ct2":["joergwegener","Jörg Wegener"],
"m2f5gn2lut66n7a5nizb2uhd":["juerg44","Jürg Wegelin"],
"fsczyoyanknay55nzyydk36a":["kaiweg","Kai Wegrich"],
"ge5tqze2izwgu4kqnj6wqfyb":["kenwegrzyn","Ken Wegrzyn"],
"wodrzznybh7dxqehyonzf7hz":["kilianwegner","Kilian Wegner"],
"dobfignig75qir2wsxytxcpa":["kironawege","Kirona Wege"],
"466qdkemewfqhgmfb5vht5vg":["krakelkrakel","...am Arsch vorbei geht auch ein Weg "],
"h5yobj4aysalrp7y2e6xlhuy":["lernwegweiser","LernWegWeiser"],
"iouwgwxysnk2dwfjp6pt7pan":["markus.is","Markus Wegscheider"],
"53osscso5bcbr5u7hi3tib7t":["marjaninedi","Marjan van de Weg "],
"bkgbmtgdiasjg76ilsofrwb3":["markwege.de","Mark Wege 📯 markwege@mastodon.social ☮︎ 6 x 💉"],
"oo5cdmhr6cjbd2t77u6gbkyr":["marenwegner","Maren Wegner"],
"ncdfyli6zrh5fs77epfbhtpc":["mdbdesgrauens","Wählerwille des PiS-Wegmachens!"],
"yk7rf6qwggj4jopplpdno7yr":["megparsec","Megan Wegenke"],
"jw2whzk4e7cckkv5mei6xrpw":["miteinemwisch","Mit einem Wisch ist alles weg"],
"ms6kdlm7sqxzkbpyfr2xqqhl":["mwegemann","Mirko Wegemann"],
"x2cigw22jtwomwlly6f7cneq":["natewegehaupt","Nate Wegehaupt "],
"hc2b5psbfx7vjloo6qjcsvjg":["nbjule","Jutta Wegner"],
"dw3om74yu5xbppk7ix5egu5v":["neuewegedeslernens","Neue Wege des Lernens e. V."],
"vrpt2gyachjgrpjmba7wwtff":["niclaswegener","Niclas Wegener"],
"fpxbobwml4k4hjre24l26pv4":["numbra","Malte Wegmann"],
"qfl2lmyzcbrislgelwdf6ijf":["passingastrangr","entrueckt am wegesrand "],
"ry24so2ss2qjaraenjqrh3df":"pa3weg",
"as6bv7a7g7cijrwrto637xtw":["panwegman1004","Pan Wegman "],
"xqtaqwvitpirxxlfn5oibblq":["pcspenden","Computer spenden statt wegwerfen"],
"44vvgthphrdpzl4qljom7bby":["peterkarlweger","Peter Karl Weger "],
"hv5dlyq5ovxdr42uljewjsv7":["peweger","Pe Weger "],
"ktped2cj4amxw62hspyiwwed":["producertory","Tory Wegerski"],
"v4cd6rd45fxt7fd7ksgdxqsd":["productionsound","Christian Wegner"],
"lfnmuqsdqzp5cryljbo4tprp":["proldeweghuis","Pirmin Olde Weghuis"],
"2cmli2veasfthbfxq3jkpo5q":["pvandeweghe","Pierre van de Weghe "],
"2fr24m2w67j4r7a5t4kgd2mg":["skullhaus","Ray Wegner - Skullhaus Studios"],
"pkemupytzucu2jrrvprs2m6f":["susannewegscheider","Susanne Wegscheider"],
"eow3kksbn7u5cssfzqqhl4nk":["suennerklaas","Sünnerklaas - KratzeKatzer - Treibt den Kessel und nimmt was weg"],
"rvlrckjf7vpf7d6yjtzogruu":["swegmann","Simone Wegmann"],
"7ypc5k4wrhxhbyqwlejjxkow":["sweg","𝓢weg🍀"],
"jxy27rbnc2pb3orvquai3vb3":["sylvos","Sylvos wegen des statt wegen dem "],
"6r7gtxgoin3d6wt37gp7muz6":["undwegwarsie","Und weg war sie "],
"heggognpparwhtvsrj3r4vz4":["vonwegen","M. von Wegen"],
"yrlo3qxtl3vh4jx2qreaeiew":["wadewegner.com","Wade Wegner"],
"uy3mpm56ityhq37cto3kqci4":["walterweg","Walter Weg "],
"4fv2vxtl3jjbzvcwzuelgmod":["wegladlyfeast","ana"],
"5y3voomewah2bxlyer66o5xj":["wega","wega"],
"ifwribkj5kijc3hxondp7uhe":["wegschaider","Klaudia Wegschaider"],
"s3zeoql5boafyfduhj2r3kee":["wegohigh","해호"],
"xb2qjbzewdvgihcnetn3zwq7":["wegr","wegr"],
"zkseceh7k7sjadobzn34l2gc":"weg9ndba",
"uozcxpdxf7csytsazvnoffqj":"weggles",
"klyjoetnklkrbf6vryy5qyw2":"wegotthiscovered",
"cse7whv37gueoevldbbbu7n4":["weggpudding","wegg"],
"tljvqzbwqhnhqgzc4f4hody6":["wegenwacht4447","Wegenwacht4447"],
"izgkqcorb3q24uxzyu35yj4x":["weg","weg"],
"puvmavt5fmx4uea7gknztapw":"wegenmic",
"e6thiwlmyhfgrya2fs2bnygg":"wegetitchris",
"nvlavskcrqwwedihad3tuzvm":["wegeekgirls","We Geek Girls"],
"7jf3uuw4q5i5ulsif3ugctqu":["wegjd","91"],
"ei73nooxmxnoufbr5cne3oj6":["wegotthejosh","josh"],
"sgfp2pk73sirbhixe73cbnbp":["wegoscloset","②"],
"vxsycuatrbwr5eipribtg52w":["wegulawity","with some regularity"],
"ncb2p5is2e3uekor57djnziz":["wegfava","Weg Fava"],
"mikb77fplzjhbrfggervgikv":"wegas",
"q3uh5in4vogheeirxbpdgtyy":["wegrowatdawn","wegrowatdawn"],
"hcpoj7pueiiqyomy6qlnsbhh":"wegner",
"t64pjlnxb2pas4bt4nrvnchr":["wegetdubbed","WGD "],
"s3shqt2qjfhe3cz47e3sxcgk":["wegoleft","간다왼쪽으로"],
"o72fpl2mlix7t6lmrvo3nblf":["wegriz","Wegriz"],
"nw6ym6xpmjfteefwkwcuk333":"weglaweg",
"sg3v27c6234gainsli4xgojq":"wega710",
"jna7kzn5tlrs45d6usitz6yw":["wegottapod","We Gotta Podcast"],
"bpvdfupafg3vcex4bh2d3alt":"wegener",
"ciaoh4iclklt3ygd2pv6q7vv":["wegendal","William Egendal"],
"5ua23cof3siogw6bcbindfh7":["weggetor","weggetor"],
"fgeie2ij4bhcsosh7dblcuta":["wegner.io","Jochen Wegner"],
"ykklqxejwfhhjnq6yclgyofn":["wegelagerer0815","Wegelagerer0815"],
"w3cb6szstdv7f2zgfiqudx3p":"wegvid",
"hs6iv67uxyqa2wnfc7d55pdn":["wegg","Wegg! "],
"teztsyvuwusungik5qjoevqy":"weg5st0",
"jdp3pbleknuhxcd5i2lfvydd":"wegnth01",
"prx5dlaxo3difqpzoqjfrziw":["wegduckstein","Weg Duck-Stein"],
"oqirjfsijzb4yd2peqtu24p7":"wegreen",
"j3gbpckwqktjcgstmtq74tlh":["wege","Jesper Berglund"],
"n7cdvskcjho5wfi5gopsokfu":["wegeek","WeGeek"],
"iwnahrghtlwvoakv3dyc3or6":["weggla","Weggla"],
"mrm7sytiyqqq74jwkbw7abf4":"wegotbots",
"rwjliudr5ioudv2g4ac32i3l":["wegi72","f®eigeist™📯"],
"a47zjbmopijsu7qgdvzvt2rq":["wegehaupt","Bockwurstboy"],
"3rit4zd46fy362diyuhqfypi":"wegmannm",
"5yypvem3hiw4wpzc6vcujst5":["wilmaweg","WilmaWeg"],
"giynjhq7ei4hmcalsmqa7zzy":["yuelzisch","Löwegeborener"],
"wpthszrg5zzh5jtu4zf5bmlw":["ywegelin","Yves Wegelin"]
}
