{
"r3f2w62c3eckl72twsrq456g":["colinwmdnew","ColinWmd"],
"gzjo7hgg2unvqst7kvu6wyig":["n0wmd","Don Pearce"],
"bkxxgxnxxcog3dbb5tzw4agz":["thatwmd","WMD"],
"ywbhryhbrchkg7gn4haccp7b":["wmdsearcher","wmdsearcher"],
"h3lfmo3tyhazaoq3h2grp5av":["wmd","will depue"],
"rhjmtngnue4lnttbgvf7ghap":["wmd4x","Will Hunting "],
"pgj6pyxxq45wtizrxon65xbq":["wmdtucker","will tucker"],
"r4nzzsdilfwyiwhv2ts4wvky":["wmdiscovery93","William Mai"],
"gof2ust4sfsef3v4pma2vyz4":"wmdell",
"i3756s62aeav5j5gdqox7qhc":["wmdmark","Mark Johnson"],
"j7l4ihqoqvzn5oplyltrmoz4":["wmd505","Walter Duran"],
"knb36z2nr5gi6epoqcxss4gd":["wmdeeznuts","George Busch Light"],
"wepldv3posk2rrpcuam6xirl":"wmdaggie"
}
